[{ "group": "nodes", "data": { "id": "16" } },{ "group": "nodes", "data": { "id": "org.joda.money.format.LiteralPrinterParser", "parent": "16" } },{ "group": "edges", "data": { "id": "16_13", "source": "16", "target": "13" } },{ "group": "edges", "data": { "id": "org.joda.money.format.LiteralPrinterParser_org.joda.money.format.MoneyParser", "source": "org.joda.money.format.LiteralPrinterParser", "target": "org.joda.money.format.MoneyParser" } },{ "group": "edges", "data": { "id": "16_27", "source": "16", "target": "27" } },{ "group": "edges", "data": { "id": "16_15", "source": "16", "target": "15" } },{ "group": "nodes", "data": { "id": "org.joda.money.format.MoneyParser", "parent": "16" } },{ "group": "nodes", "data": { "id": "17" } },{ "group": "nodes", "data": { "id": "org.joda.money.format.MoneyFormatterBuilder", "parent": "17" } },{ "group": "edges", "data": { "id": "17_13", "source": "17", "target": "13" } },{ "group": "edges", "data": { "id": "17_16", "source": "17", "target": "16" } },{ "group": "edges", "data": { "id": "17_11", "source": "17", "target": "11" } },{ "group": "edges", "data": { "id": "17_19", "source": "17", "target": "19" } },{ "group": "edges", "data": { "id": "org.joda.money.format.MoneyFormatterBuilder_org.joda.money.format.MoneyFormatterBuilder$SingletonPrinters", "source": "org.joda.money.format.MoneyFormatterBuilder", "target": "org.joda.money.format.MoneyFormatterBuilder$SingletonPrinters" } },{ "group": "edges", "data": { "id": "org.joda.money.format.MoneyFormatterBuilder_org.joda.money.format.MoneyFormatterBuilder$Singletons$2", "source": "org.joda.money.format.MoneyFormatterBuilder", "target": "org.joda.money.format.MoneyFormatterBuilder$Singletons$2" } },{ "group": "edges", "data": { "id": "17_7", "source": "17", "target": "7" } },{ "group": "nodes", "data": { "id": "org.joda.money.format.MoneyFormatterBuilder$SingletonPrinters", "parent": "17" } },{ "group": "edges", "data": { "id": "17_27", "source": "17", "target": "27" } },{ "group": "edges", "data": { "id": "17_26", "source": "17", "target": "26" } },{ "group": "nodes", "data": { "id": "org.joda.money.format.MoneyFormatterBuilder$Singletons$2", "parent": "17" } },{ "group": "edges", "data": { "id": "17_15", "source": "17", "target": "15" } },{ "group": "nodes", "data": { "id": "19" } },{ "group": "nodes", "data": { "id": "org.joda.money.format.MoneyFormatterBuilder$Singletons", "parent": "19" } },{ "group": "edges", "data": { "id": "19_13", "source": "19", "target": "13" } },{ "group": "edges", "data": { "id": "19_16", "source": "19", "target": "16" } },{ "group": "edges", "data": { "id": "19_7", "source": "19", "target": "7" } },{ "group": "edges", "data": { "id": "org.joda.money.format.MoneyFormatterBuilder$Singletons_org.joda.money.format.MoneyFormatterBuilder$Singletons$3", "source": "org.joda.money.format.MoneyFormatterBuilder$Singletons", "target": "org.joda.money.format.MoneyFormatterBuilder$Singletons$3" } },{ "group": "nodes", "data": { "id": "org.joda.money.format.MoneyFormatterBuilder$Singletons$3", "parent": "19" } },{ "group": "edges", "data": { "id": "19_27", "source": "19", "target": "27" } },{ "group": "edges", "data": { "id": "19_15", "source": "19", "target": "15" } },{ "group": "edges", "data": { "id": "19_26", "source": "19", "target": "26" } },{ "group": "nodes", "data": { "id": "5" } },{ "group": "nodes", "data": { "id": "org.joda.money.DefaultCurrencyUnitDataProvider", "parent": "5" } },{ "group": "edges", "data": { "id": "org.joda.money.DefaultCurrencyUnitDataProvider_org.joda.money.CurrencyUnitDataProvider", "source": "org.joda.money.DefaultCurrencyUnitDataProvider", "target": "org.joda.money.CurrencyUnitDataProvider" } },{ "group": "nodes", "data": { "id": "org.joda.money.CurrencyUnitDataProvider", "parent": "5" } },{ "group": "edges", "data": { "id": "5_26", "source": "5", "target": "26" } },{ "group": "nodes", "data": { "id": "7" } },{ "group": "nodes", "data": { "id": "org.joda.money.format.MoneyFormatterBuilder$Singletons$1", "parent": "7" } },{ "group": "edges", "data": { "id": "7_13", "source": "7", "target": "13" } },{ "group": "edges", "data": { "id": "7_27", "source": "7", "target": "27" } },{ "group": "edges", "data": { "id": "7_15", "source": "7", "target": "15" } },{ "group": "edges", "data": { "id": "org.joda.money.format.MoneyFormatterBuilder$Singletons$1_org.joda.money.IllegalCurrencyException", "source": "org.joda.money.format.MoneyFormatterBuilder$Singletons$1", "target": "org.joda.money.IllegalCurrencyException" } },{ "group": "edges", "data": { "id": "7_26", "source": "7", "target": "26" } },{ "group": "nodes", "data": { "id": "org.joda.money.IllegalCurrencyException", "parent": "7" } },{ "group": "nodes", "data": { "id": "26" } },{ "group": "nodes", "data": { "id": "org.joda.money.Ser", "parent": "26" } },{ "group": "edges", "data": { "id": "26_27", "source": "26", "target": "27" } },{ "group": "edges", "data": { "id": "org.joda.money.Ser_org.joda.money.CurrencyUnit", "source": "org.joda.money.Ser", "target": "org.joda.money.CurrencyUnit" } },{ "group": "nodes", "data": { "id": "org.joda.money.CurrencyUnit", "parent": "26" } },{ "group": "nodes", "data": { "id": "org.joda.money.CurrencyMismatchException", "parent": "26" } },{ "group": "edges", "data": { "id": "org.joda.money.CurrencyMismatchException_org.joda.money.CurrencyUnit", "source": "org.joda.money.CurrencyMismatchException", "target": "org.joda.money.CurrencyUnit" } },{ "group": "nodes", "data": { "id": "11" } },{ "group": "nodes", "data": { "id": "org.joda.money.format.MoneyAmountStyle", "parent": "11" } },{ "group": "edges", "data": { "id": "org.joda.money.format.MoneyAmountStyle_org.joda.money.format.GroupingStyle", "source": "org.joda.money.format.MoneyAmountStyle", "target": "org.joda.money.format.GroupingStyle" } },{ "group": "edges", "data": { "id": "11_13", "source": "11", "target": "13" } },{ "group": "nodes", "data": { "id": "org.joda.money.format.AmountPrinterParser", "parent": "11" } },{ "group": "edges", "data": { "id": "11_16", "source": "11", "target": "16" } },{ "group": "edges", "data": { "id": "org.joda.money.format.AmountPrinterParser_org.joda.money.format.MoneyAmountStyle", "source": "org.joda.money.format.AmountPrinterParser", "target": "org.joda.money.format.MoneyAmountStyle" } },{ "group": "edges", "data": { "id": "11_27", "source": "11", "target": "27" } },{ "group": "edges", "data": { "id": "11_15", "source": "11", "target": "15" } },{ "group": "edges", "data": { "id": "org.joda.money.format.AmountPrinterParser_org.joda.money.format.GroupingStyle", "source": "org.joda.money.format.AmountPrinterParser", "target": "org.joda.money.format.GroupingStyle" } },{ "group": "nodes", "data": { "id": "org.joda.money.format.GroupingStyle", "parent": "11" } },{ "group": "nodes", "data": { "id": "27" } },{ "group": "nodes", "data": { "id": "org.joda.money.BigMoneyProvider", "parent": "27" } },{ "group": "edges", "data": { "id": "org.joda.money.BigMoneyProvider_org.joda.money.BigMoney", "source": "org.joda.money.BigMoneyProvider", "target": "org.joda.money.BigMoney" } },{ "group": "nodes", "data": { "id": "org.joda.money.MoneyUtils", "parent": "27" } },{ "group": "edges", "data": { "id": "org.joda.money.MoneyUtils_org.joda.money.BigMoneyProvider", "source": "org.joda.money.MoneyUtils", "target": "org.joda.money.BigMoneyProvider" } },{ "group": "edges", "data": { "id": "org.joda.money.MoneyUtils_org.joda.money.Money", "source": "org.joda.money.MoneyUtils", "target": "org.joda.money.Money" } },{ "group": "edges", "data": { "id": "org.joda.money.MoneyUtils_org.joda.money.BigMoney", "source": "org.joda.money.MoneyUtils", "target": "org.joda.money.BigMoney" } },{ "group": "nodes", "data": { "id": "org.joda.money.Money", "parent": "27" } },{ "group": "edges", "data": { "id": "org.joda.money.Money_org.joda.money.BigMoneyProvider", "source": "org.joda.money.Money", "target": "org.joda.money.BigMoneyProvider" } },{ "group": "edges", "data": { "id": "org.joda.money.Money_org.joda.money.BigMoney", "source": "org.joda.money.Money", "target": "org.joda.money.BigMoney" } },{ "group": "nodes", "data": { "id": "org.joda.money.BigMoney", "parent": "27" } },{ "group": "nodes", "data": { "id": "13" } },{ "group": "nodes", "data": { "id": "org.joda.money.format.MoneyFormatter", "parent": "13" } },{ "group": "edges", "data": { "id": "org.joda.money.format.MoneyFormatter_org.joda.money.format.MultiPrinterParser", "source": "org.joda.money.format.MoneyFormatter", "target": "org.joda.money.format.MultiPrinterParser" } },{ "group": "edges", "data": { "id": "org.joda.money.format.MoneyFormatter_org.joda.money.format.MoneyPrinter", "source": "org.joda.money.format.MoneyFormatter", "target": "org.joda.money.format.MoneyPrinter" } },{ "group": "edges", "data": { "id": "13_27", "source": "13", "target": "27" } },{ "group": "edges", "data": { "id": "org.joda.money.format.MoneyFormatter_org.joda.money.format.MoneyPrintContext", "source": "org.joda.money.format.MoneyFormatter", "target": "org.joda.money.format.MoneyPrintContext" } },{ "group": "edges", "data": { "id": "13_15", "source": "13", "target": "15" } },{ "group": "nodes", "data": { "id": "org.joda.money.format.MoneyPrintContext", "parent": "13" } },{ "group": "nodes", "data": { "id": "org.joda.money.format.SignedPrinterParser", "parent": "13" } },{ "group": "edges", "data": { "id": "org.joda.money.format.SignedPrinterParser_org.joda.money.format.MoneyPrinter", "source": "org.joda.money.format.SignedPrinterParser", "target": "org.joda.money.format.MoneyPrinter" } },{ "group": "edges", "data": { "id": "org.joda.money.format.SignedPrinterParser_org.joda.money.format.MoneyFormatter", "source": "org.joda.money.format.SignedPrinterParser", "target": "org.joda.money.format.MoneyFormatter" } },{ "group": "edges", "data": { "id": "org.joda.money.format.SignedPrinterParser_org.joda.money.format.MoneyPrintContext", "source": "org.joda.money.format.SignedPrinterParser", "target": "org.joda.money.format.MoneyPrintContext" } },{ "group": "edges", "data": { "id": "org.joda.money.format.SignedPrinterParser_org.joda.money.format.MultiPrinterParser", "source": "org.joda.money.format.SignedPrinterParser", "target": "org.joda.money.format.MultiPrinterParser" } },{ "group": "nodes", "data": { "id": "org.joda.money.format.MoneyPrinter", "parent": "13" } },{ "group": "edges", "data": { "id": "org.joda.money.format.MoneyPrinter_org.joda.money.format.MoneyPrintContext", "source": "org.joda.money.format.MoneyPrinter", "target": "org.joda.money.format.MoneyPrintContext" } },{ "group": "nodes", "data": { "id": "org.joda.money.format.MultiPrinterParser", "parent": "13" } },{ "group": "edges", "data": { "id": "org.joda.money.format.MultiPrinterParser_org.joda.money.format.MoneyPrinter", "source": "org.joda.money.format.MultiPrinterParser", "target": "org.joda.money.format.MoneyPrinter" } },{ "group": "edges", "data": { "id": "org.joda.money.format.MultiPrinterParser_org.joda.money.format.MoneyPrintContext", "source": "org.joda.money.format.MultiPrinterParser", "target": "org.joda.money.format.MoneyPrintContext" } },{ "group": "nodes", "data": { "id": "15" } },{ "group": "nodes", "data": { "id": "org.joda.money.format.MoneyParseContext", "parent": "15" } },{ "group": "edges", "data": { "id": "15_26", "source": "15", "target": "26" } },{ "group": "edges", "data": { "id": "15_27", "source": "15", "target": "27" } },{ "group": "edges", "data": { "id": "org.joda.money.format.MoneyParseContext_org.joda.money.format.MoneyFormatException", "source": "org.joda.money.format.MoneyParseContext", "target": "org.joda.money.format.MoneyFormatException" } },{ "group": "nodes", "data": { "id": "org.joda.money.format.MoneyFormatException", "parent": "15" } }]
