[{ "group": "nodes", "data": { "id": "1" } },{ "group": "nodes", "data": { "id": "io.moquette.broker.NewNettyAcceptor$5", "parent": "1" } },{ "group": "edges", "data": { "id": "1_118", "source": "1", "target": "118" } },{ "group": "edges", "data": { "id": "1_143", "source": "1", "target": "143" } },{ "group": "edges", "data": { "id": "1_181", "source": "1", "target": "181" } },{ "group": "edges", "data": { "id": "1_101", "source": "1", "target": "101" } },{ "group": "edges", "data": { "id": "1_70", "source": "1", "target": "70" } },{ "group": "edges", "data": { "id": "1_69", "source": "1", "target": "69" } },{ "group": "edges", "data": { "id": "1_39", "source": "1", "target": "39" } },{ "group": "nodes", "data": { "id": "3" } },{ "group": "nodes", "data": { "id": "io.moquette.broker.unsafequeues.PagedFilesAllocator", "parent": "3" } },{ "group": "edges", "data": { "id": "3_5", "source": "3", "target": "5" } },{ "group": "edges", "data": { "id": "3_141", "source": "3", "target": "141" } },{ "group": "edges", "data": { "id": "3_116", "source": "3", "target": "116" } },{ "group": "edges", "data": { "id": "3_149", "source": "3", "target": "149" } },{ "group": "edges", "data": { "id": "3_10", "source": "3", "target": "10" } },{ "group": "nodes", "data": { "id": "io.moquette.broker.unsafequeues.QueuePool$SegmentAllocationCallback", "parent": "3" } },{ "group": "edges", "data": { "id": "3_147", "source": "3", "target": "147" } },{ "group": "edges", "data": { "id": "io.moquette.broker.unsafequeues.QueuePool$SegmentAllocationCallback_io.moquette.broker.unsafequeues.PagedFilesAllocator", "source": "io.moquette.broker.unsafequeues.QueuePool$SegmentAllocationCallback", "target": "io.moquette.broker.unsafequeues.PagedFilesAllocator" } },{ "group": "nodes", "data": { "id": "4" } },{ "group": "nodes", "data": { "id": "io.moquette.broker.AutoFlushHandler$WriterIdleTimeoutTask", "parent": "4" } },{ "group": "edges", "data": { "id": "io.moquette.broker.AutoFlushHandler$WriterIdleTimeoutTask_io.moquette.broker.AutoFlushHandler", "source": "io.moquette.broker.AutoFlushHandler$WriterIdleTimeoutTask", "target": "io.moquette.broker.AutoFlushHandler" } },{ "group": "nodes", "data": { "id": "io.moquette.broker.AutoFlushHandler", "parent": "4" } },{ "group": "edges", "data": { "id": "4_143", "source": "4", "target": "143" } },{ "group": "nodes", "data": { "id": "5" } },{ "group": "nodes", "data": { "id": "io.moquette.broker.security.ACLFileParser", "parent": "5" } },{ "group": "edges", "data": { "id": "5_176", "source": "5", "target": "176" } },{ "group": "nodes", "data": { "id": "io.moquette.broker.unsafequeues.SegmentAllocator", "parent": "5" } },{ "group": "edges", "data": { "id": "5_141", "source": "5", "target": "141" } },{ "group": "edges", "data": { "id": "5_116", "source": "5", "target": "116" } },{ "group": "nodes", "data": { "id": "6" } },{ "group": "nodes", "data": { "id": "io.moquette.broker.config.FluentConfig$KeyStoreType", "parent": "6" } },{ "group": "edges", "data": { "id": "6_61", "source": "6", "target": "61" } },{ "group": "nodes", "data": { "id": "io.moquette.broker.config.FluentConfig$PersistentQueueType", "parent": "6" } },{ "group": "nodes", "data": { "id": "9" } },{ "group": "nodes", "data": { "id": "io.moquette.broker.SessionRegistry$CreationModeEnum", "parent": "9" } },{ "group": "edges", "data": { "id": "io.moquette.broker.SessionRegistry$CreationModeEnum_io.moquette.broker.SessionRegistry", "source": "io.moquette.broker.SessionRegistry$CreationModeEnum", "target": "io.moquette.broker.SessionRegistry" } },{ "group": "nodes", "data": { "id": "io.moquette.broker.SessionRegistry$PubRelMarker", "parent": "9" } },{ "group": "edges", "data": { "id": "9_112", "source": "9", "target": "112" } },{ "group": "edges", "data": { "id": "io.moquette.broker.SessionRegistry$PubRelMarker_io.moquette.broker.SessionRegistry", "source": "io.moquette.broker.SessionRegistry$PubRelMarker", "target": "io.moquette.broker.SessionRegistry" } },{ "group": "nodes", "data": { "id": "io.moquette.broker.SessionRegistry", "parent": "9" } },{ "group": "edges", "data": { "id": "9_171", "source": "9", "target": "171" } },{ "group": "edges", "data": { "id": "9_34", "source": "9", "target": "34" } },{ "group": "edges", "data": { "id": "9_71", "source": "9", "target": "71" } },{ "group": "edges", "data": { "id": "9_60", "source": "9", "target": "60" } },{ "group": "edges", "data": { "id": "9_88", "source": "9", "target": "88" } },{ "group": "edges", "data": { "id": "9_139", "source": "9", "target": "139" } },{ "group": "edges", "data": { "id": "9_200", "source": "9", "target": "200" } },{ "group": "edges", "data": { "id": "9_70", "source": "9", "target": "70" } },{ "group": "edges", "data": { "id": "9_175", "source": "9", "target": "175" } },{ "group": "edges", "data": { "id": "9_110", "source": "9", "target": "110" } },{ "group": "edges", "data": { "id": "9_173", "source": "9", "target": "173" } },{ "group": "edges", "data": { "id": "9_107", "source": "9", "target": "107" } },{ "group": "edges", "data": { "id": "9_185", "source": "9", "target": "185" } },{ "group": "edges", "data": { "id": "9_162", "source": "9", "target": "162" } },{ "group": "edges", "data": { "id": "9_73", "source": "9", "target": "73" } },{ "group": "edges", "data": { "id": "9_125", "source": "9", "target": "125" } },{ "group": "edges", "data": { "id": "9_129", "source": "9", "target": "129" } },{ "group": "edges", "data": { "id": "9_68", "source": "9", "target": "68" } },{ "group": "edges", "data": { "id": "9_122", "source": "9", "target": "122" } },{ "group": "edges", "data": { "id": "9_167", "source": "9", "target": "167" } },{ "group": "edges", "data": { "id": "9_152", "source": "9", "target": "152" } },{ "group": "nodes", "data": { "id": "10" } },{ "group": "nodes", "data": { "id": "io.moquette.broker.unsafequeues.PagedFilesAllocator$AllocationListener", "parent": "10" } },{ "group": "edges", "data": { "id": "10_141", "source": "10", "target": "141" } },{ "group": "nodes", "data": { "id": "io.moquette.persistence.H2SessionsRepository", "parent": "10" } },{ "group": "edges", "data": { "id": "10_139", "source": "10", "target": "139" } },{ "group": "edges", "data": { "id": "10_71", "source": "10", "target": "71" } },{ "group": "edges", "data": { "id": "10_107", "source": "10", "target": "107" } },{ "group": "edges", "data": { "id": "10_13", "source": "10", "target": "13" } },{ "group": "edges", "data": { "id": "10_185", "source": "10", "target": "185" } },{ "group": "nodes", "data": { "id": "12" } },{ "group": "nodes", "data": { "id": "io.moquette.broker.config.ConfigurationParser", "parent": "12" } },{ "group": "nodes", "data": { "id": "io.moquette.broker.config.IResourceLoader$ResourceIsDirectoryException", "parent": "12" } },{ "group": "edges", "data": { "id": "12_109", "source": "12", "target": "109" } },{ "group": "nodes", "data": { "id": "13" } },{ "group": "nodes", "data": { "id": "io.moquette.persistence.H2SessionsRepository$DurationDataValueType", "parent": "13" } },{ "group": "edges", "data": { "id": "13_185", "source": "13", "target": "185" } },{ "group": "nodes", "data": { "id": "io.moquette.persistence.H2SessionsRepository$SessionDataValueType", "parent": "13" } },{ "group": "edges", "data": { "id": "13_71", "source": "13", "target": "71" } },{ "group": "edges", "data": { "id": "13_107", "source": "13", "target": "107" } },{ "group": "edges", "data": { "id": "13_139", "source": "13", "target": "139" } },{ "group": "nodes", "data": { "id": "io.moquette.persistence.H2SessionsRepository$UserPropertiesDataValueType", "parent": "13" } },{ "group": "nodes", "data": { "id": "14" } },{ "group": "nodes", "data": { "id": "io.moquette.persistence.SerdesUtils$1", "parent": "14" } },{ "group": "edges", "data": { "id": "14_72", "source": "14", "target": "72" } },{ "group": "edges", "data": { "id": "io.moquette.persistence.SerdesUtils$1_io.moquette.persistence.SerdesUtils", "source": "io.moquette.persistence.SerdesUtils$1", "target": "io.moquette.persistence.SerdesUtils" } },{ "group": "nodes", "data": { "id": "io.moquette.persistence.SerdesUtils", "parent": "14" } },{ "group": "nodes", "data": { "id": "21" } },{ "group": "nodes", "data": { "id": "io.moquette.broker.InflightResender", "parent": "21" } },{ "group": "edges", "data": { "id": "21_193", "source": "21", "target": "193" } },{ "group": "edges", "data": { "id": "21_143", "source": "21", "target": "143" } },{ "group": "edges", "data": { "id": "21_180", "source": "21", "target": "180" } },{ "group": "nodes", "data": { "id": "23" } },{ "group": "nodes", "data": { "id": "io.moquette.broker.MQTTConnection$ErrorCodeException", "parent": "23" } },{ "group": "edges", "data": { "id": "23_73", "source": "23", "target": "73" } },{ "group": "nodes", "data": { "id": "24" } },{ "group": "nodes", "data": { "id": "io.moquette.persistence.ByteBufDataType", "parent": "24" } },{ "group": "edges", "data": { "id": "24_68", "source": "24", "target": "68" } },{ "group": "nodes", "data": { "id": "25" } },{ "group": "nodes", "data": { "id": "io.moquette.broker.config.FluentConfig$1", "parent": "25" } },{ "group": "edges", "data": { "id": "25_61", "source": "25", "target": "61" } },{ "group": "nodes", "data": { "id": "26" } },{ "group": "nodes", "data": { "id": "io.moquette.broker.security.PemUtils$PemWriter", "parent": "26" } },{ "group": "edges", "data": { "id": "io.moquette.broker.security.PemUtils$PemWriter_io.moquette.broker.security.PemUtils", "source": "io.moquette.broker.security.PemUtils$PemWriter", "target": "io.moquette.broker.security.PemUtils" } },{ "group": "nodes", "data": { "id": "io.moquette.broker.security.PemUtils", "parent": "26" } },{ "group": "nodes", "data": { "id": "29" } },{ "group": "nodes", "data": { "id": "io.moquette.interception.InterceptHandler", "parent": "29" } },{ "group": "edges", "data": { "id": "29_32", "source": "29", "target": "32" } },{ "group": "edges", "data": { "id": "29_168", "source": "29", "target": "168" } },{ "group": "edges", "data": { "id": "29_169", "source": "29", "target": "169" } },{ "group": "edges", "data": { "id": "29_173", "source": "29", "target": "173" } },{ "group": "edges", "data": { "id": "29_124", "source": "29", "target": "124" } },{ "group": "edges", "data": { "id": "29_51", "source": "29", "target": "51" } },{ "group": "nodes", "data": { "id": "io.moquette.logging.LoggingUtils", "parent": "29" } },{ "group": "edges", "data": { "id": "io.moquette.logging.LoggingUtils_io.moquette.interception.InterceptHandler", "source": "io.moquette.logging.LoggingUtils", "target": "io.moquette.interception.InterceptHandler" } },{ "group": "nodes", "data": { "id": "30" } },{ "group": "nodes", "data": { "id": "io.moquette.broker.Utils$Couple", "parent": "30" } },{ "group": "edges", "data": { "id": "30_68", "source": "30", "target": "68" } },{ "group": "nodes", "data": { "id": "io.moquette.persistence.MemorySubscriptionsRepository", "parent": "30" } },{ "group": "edges", "data": { "id": "30_194", "source": "30", "target": "194" } },{ "group": "edges", "data": { "id": "30_173", "source": "30", "target": "173" } },{ "group": "edges", "data": { "id": "io.moquette.persistence.MemorySubscriptionsRepository_io.moquette.broker.Utils$Couple", "source": "io.moquette.persistence.MemorySubscriptionsRepository", "target": "io.moquette.broker.Utils$Couple" } },{ "group": "edges", "data": { "id": "30_157", "source": "30", "target": "157" } },{ "group": "edges", "data": { "id": "30_125", "source": "30", "target": "125" } },{ "group": "edges", "data": { "id": "30_146", "source": "30", "target": "146" } },{ "group": "edges", "data": { "id": "30_167", "source": "30", "target": "167" } },{ "group": "nodes", "data": { "id": "31" } },{ "group": "nodes", "data": { "id": "io.moquette.broker.PostOffice$SharedSubscriptionData", "parent": "31" } },{ "group": "edges", "data": { "id": "31_157", "source": "31", "target": "157" } },{ "group": "edges", "data": { "id": "31_125", "source": "31", "target": "125" } },{ "group": "edges", "data": { "id": "io.moquette.broker.PostOffice$SharedSubscriptionData_io.moquette.broker.SharedSubscriptionUtils", "source": "io.moquette.broker.PostOffice$SharedSubscriptionData", "target": "io.moquette.broker.SharedSubscriptionUtils" } },{ "group": "edges", "data": { "id": "31_167", "source": "31", "target": "167" } },{ "group": "nodes", "data": { "id": "io.moquette.broker.SharedSubscriptionUtils", "parent": "31" } },{ "group": "nodes", "data": { "id": "32" } },{ "group": "nodes", "data": { "id": "io.moquette.interception.messages.InterceptConnectMessage", "parent": "32" } },{ "group": "edges", "data": { "id": "32_169", "source": "32", "target": "169" } },{ "group": "nodes", "data": { "id": "34" } },{ "group": "nodes", "data": { "id": "io.moquette.broker.scheduler.ScheduledExpirationService", "parent": "34" } },{ "group": "edges", "data": { "id": "34_96", "source": "34", "target": "96" } },{ "group": "edges", "data": { "id": "34_71", "source": "34", "target": "71" } },{ "group": "nodes", "data": { "id": "36" } },{ "group": "nodes", "data": { "id": "io.moquette.broker.unsafequeues.Queue$1", "parent": "36" } },{ "group": "edges", "data": { "id": "io.moquette.broker.unsafequeues.Queue$1_io.moquette.broker.unsafequeues.Queue", "source": "io.moquette.broker.unsafequeues.Queue$1", "target": "io.moquette.broker.unsafequeues.Queue" } },{ "group": "nodes", "data": { "id": "io.moquette.broker.unsafequeues.Queue$CrossSegmentHeaderResult", "parent": "36" } },{ "group": "edges", "data": { "id": "36_141", "source": "36", "target": "141" } },{ "group": "edges", "data": { "id": "io.moquette.broker.unsafequeues.Queue$CrossSegmentHeaderResult_io.moquette.broker.unsafequeues.Queue$1", "source": "io.moquette.broker.unsafequeues.Queue$CrossSegmentHeaderResult", "target": "io.moquette.broker.unsafequeues.Queue$1" } },{ "group": "edges", "data": { "id": "io.moquette.broker.unsafequeues.Queue$CrossSegmentHeaderResult_io.moquette.broker.unsafequeues.Queue", "source": "io.moquette.broker.unsafequeues.Queue$CrossSegmentHeaderResult", "target": "io.moquette.broker.unsafequeues.Queue" } },{ "group": "nodes", "data": { "id": "io.moquette.broker.unsafequeues.Queue", "parent": "36" } },{ "group": "edges", "data": { "id": "36_149", "source": "36", "target": "149" } },{ "group": "edges", "data": { "id": "36_5", "source": "36", "target": "5" } },{ "group": "edges", "data": { "id": "36_10", "source": "36", "target": "10" } },{ "group": "edges", "data": { "id": "36_116", "source": "36", "target": "116" } },{ "group": "edges", "data": { "id": "36_3", "source": "36", "target": "3" } },{ "group": "nodes", "data": { "id": "37" } },{ "group": "nodes", "data": { "id": "io.moquette.broker.subscriptions.INode", "parent": "37" } },{ "group": "edges", "data": { "id": "37_190", "source": "37", "target": "190" } },{ "group": "edges", "data": { "id": "io.moquette.broker.subscriptions.INode_io.moquette.broker.subscriptions.TNode", "source": "io.moquette.broker.subscriptions.INode", "target": "io.moquette.broker.subscriptions.TNode" } },{ "group": "nodes", "data": { "id": "io.moquette.broker.subscriptions.TNode", "parent": "37" } },{ "group": "edges", "data": { "id": "37_137", "source": "37", "target": "137" } },{ "group": "edges", "data": { "id": "37_100", "source": "37", "target": "100" } },{ "group": "edges", "data": { "id": "37_157", "source": "37", "target": "157" } },{ "group": "edges", "data": { "id": "37_98", "source": "37", "target": "98" } },{ "group": "nodes", "data": { "id": "39" } },{ "group": "nodes", "data": { "id": "io.moquette.broker.NewNettyAcceptor$4", "parent": "39" } },{ "group": "edges", "data": { "id": "39_118", "source": "39", "target": "118" } },{ "group": "edges", "data": { "id": "39_143", "source": "39", "target": "143" } },{ "group": "edges", "data": { "id": "39_181", "source": "39", "target": "181" } },{ "group": "edges", "data": { "id": "39_101", "source": "39", "target": "101" } },{ "group": "edges", "data": { "id": "io.moquette.broker.NewNettyAcceptor$4_io.moquette.broker.config.IConfig", "source": "io.moquette.broker.NewNettyAcceptor$4", "target": "io.moquette.broker.config.IConfig" } },{ "group": "nodes", "data": { "id": "io.moquette.broker.config.IConfig", "parent": "39" } },{ "group": "edges", "data": { "id": "39_109", "source": "39", "target": "109" } },{ "group": "edges", "data": { "id": "39_144", "source": "39", "target": "144" } },{ "group": "nodes", "data": { "id": "43" } },{ "group": "nodes", "data": { "id": "io.moquette.broker.metrics.MessageMetricsCollector", "parent": "43" } },{ "group": "edges", "data": { "id": "43_99", "source": "43", "target": "99" } },{ "group": "nodes", "data": { "id": "45" } },{ "group": "nodes", "data": { "id": "io.moquette.broker.security.AcceptAllAuthenticator", "parent": "45" } },{ "group": "edges", "data": { "id": "io.moquette.broker.security.AcceptAllAuthenticator_io.moquette.broker.security.IAuthenticator", "source": "io.moquette.broker.security.AcceptAllAuthenticator", "target": "io.moquette.broker.security.IAuthenticator" } },{ "group": "nodes", "data": { "id": "io.moquette.broker.security.DBAuthenticator", "parent": "45" } },{ "group": "edges", "data": { "id": "io.moquette.broker.security.DBAuthenticator_io.moquette.broker.security.IAuthenticator", "source": "io.moquette.broker.security.DBAuthenticator", "target": "io.moquette.broker.security.IAuthenticator" } },{ "group": "edges", "data": { "id": "45_39", "source": "45", "target": "39" } },{ "group": "edges", "data": { "id": "45_144", "source": "45", "target": "144" } },{ "group": "nodes", "data": { "id": "io.moquette.broker.security.IAuthenticator", "parent": "45" } },{ "group": "nodes", "data": { "id": "48" } },{ "group": "nodes", "data": { "id": "io.moquette.broker.PostOffice$FailedPublishCollection$PacketId", "parent": "48" } },{ "group": "edges", "data": { "id": "io.moquette.broker.PostOffice$FailedPublishCollection$PacketId_io.moquette.broker.PostOffice$FailedPublishCollection", "source": "io.moquette.broker.PostOffice$FailedPublishCollection$PacketId", "target": "io.moquette.broker.PostOffice$FailedPublishCollection" } },{ "group": "edges", "data": { "id": "48_167", "source": "48", "target": "167" } },{ "group": "nodes", "data": { "id": "io.moquette.broker.PostOffice$FailedPublishCollection", "parent": "48" } },{ "group": "nodes", "data": { "id": "49" } },{ "group": "nodes", "data": { "id": "io.moquette.broker.Session$InFlightPacket", "parent": "49" } },{ "group": "edges", "data": { "id": "49_60", "source": "49", "target": "60" } },{ "group": "nodes", "data": { "id": "51" } },{ "group": "nodes", "data": { "id": "io.moquette.interception.Interceptor", "parent": "51" } },{ "group": "edges", "data": { "id": "51_173", "source": "51", "target": "173" } },{ "group": "edges", "data": { "id": "51_124", "source": "51", "target": "124" } },{ "group": "edges", "data": { "id": "io.moquette.interception.Interceptor_io.moquette.interception.messages.InterceptExceptionMessage", "source": "io.moquette.interception.Interceptor", "target": "io.moquette.interception.messages.InterceptExceptionMessage" } },{ "group": "nodes", "data": { "id": "io.moquette.interception.messages.InterceptExceptionMessage", "parent": "51" } },{ "group": "edges", "data": { "id": "51_168", "source": "51", "target": "168" } },{ "group": "nodes", "data": { "id": "52" } },{ "group": "nodes", "data": { "id": "io.moquette.broker.Session$1", "parent": "52" } },{ "group": "edges", "data": { "id": "52_60", "source": "52", "target": "60" } },{ "group": "nodes", "data": { "id": "53" } },{ "group": "nodes", "data": { "id": "io.moquette.broker.LimitedQuota", "parent": "53" } },{ "group": "edges", "data": { "id": "53_73", "source": "53", "target": "73" } },{ "group": "edges", "data": { "id": "53_144", "source": "53", "target": "144" } },{ "group": "nodes", "data": { "id": "55" } },{ "group": "nodes", "data": { "id": "io.moquette.broker.SessionEventLoop", "parent": "55" } },{ "group": "nodes", "data": { "id": "60" } },{ "group": "nodes", "data": { "id": "io.moquette.broker.Session$SessionStatus", "parent": "60" } },{ "group": "edges", "data": { "id": "io.moquette.broker.Session$SessionStatus_io.moquette.broker.Session", "source": "io.moquette.broker.Session$SessionStatus", "target": "io.moquette.broker.Session" } },{ "group": "nodes", "data": { "id": "io.moquette.broker.Session", "parent": "60" } },{ "group": "edges", "data": { "id": "60_175", "source": "60", "target": "175" } },{ "group": "edges", "data": { "id": "60_112", "source": "60", "target": "112" } },{ "group": "edges", "data": { "id": "60_73", "source": "60", "target": "73" } },{ "group": "edges", "data": { "id": "60_173", "source": "60", "target": "173" } },{ "group": "edges", "data": { "id": "60_71", "source": "60", "target": "71" } },{ "group": "edges", "data": { "id": "60_125", "source": "60", "target": "125" } },{ "group": "edges", "data": { "id": "60_107", "source": "60", "target": "107" } },{ "group": "edges", "data": { "id": "60_152", "source": "60", "target": "152" } },{ "group": "edges", "data": { "id": "60_144", "source": "60", "target": "144" } },{ "group": "edges", "data": { "id": "60_68", "source": "60", "target": "68" } },{ "group": "edges", "data": { "id": "60_139", "source": "60", "target": "139" } },{ "group": "nodes", "data": { "id": "61" } },{ "group": "nodes", "data": { "id": "io.moquette.broker.config.FluentConfig$CreationKind", "parent": "61" } },{ "group": "edges", "data": { "id": "io.moquette.broker.config.FluentConfig$CreationKind_io.moquette.broker.config.FluentConfig", "source": "io.moquette.broker.config.FluentConfig$CreationKind", "target": "io.moquette.broker.config.FluentConfig" } },{ "group": "nodes", "data": { "id": "io.moquette.broker.config.FluentConfig$SSLProvider", "parent": "61" } },{ "group": "edges", "data": { "id": "io.moquette.broker.config.FluentConfig$SSLProvider_io.moquette.broker.config.FluentConfig", "source": "io.moquette.broker.config.FluentConfig$SSLProvider", "target": "io.moquette.broker.config.FluentConfig" } },{ "group": "nodes", "data": { "id": "io.moquette.broker.config.FluentConfig", "parent": "61" } },{ "group": "edges", "data": { "id": "61_144", "source": "61", "target": "144" } },{ "group": "edges", "data": { "id": "61_85", "source": "61", "target": "85" } },{ "group": "edges", "data": { "id": "61_86", "source": "61", "target": "86" } },{ "group": "edges", "data": { "id": "61_39", "source": "61", "target": "39" } },{ "group": "edges", "data": { "id": "61_113", "source": "61", "target": "113" } },{ "group": "nodes", "data": { "id": "67" } },{ "group": "nodes", "data": { "id": "io.moquette.interception.messages.InterceptAcknowledgedMessage$StoredMessage", "parent": "67" } },{ "group": "edges", "data": { "id": "67_124", "source": "67", "target": "124" } },{ "group": "nodes", "data": { "id": "68" } },{ "group": "nodes", "data": { "id": "io.moquette.broker.Utils", "parent": "68" } },{ "group": "edges", "data": { "id": "68_152", "source": "68", "target": "152" } },{ "group": "nodes", "data": { "id": "io.moquette.persistence.H2SubscriptionsRepository$CoupleValueType", "parent": "68" } },{ "group": "edges", "data": { "id": "68_157", "source": "68", "target": "157" } },{ "group": "edges", "data": { "id": "68_125", "source": "68", "target": "125" } },{ "group": "edges", "data": { "id": "68_192", "source": "68", "target": "192" } },{ "group": "edges", "data": { "id": "io.moquette.persistence.H2SubscriptionsRepository$CoupleValueType_io.moquette.broker.Utils", "source": "io.moquette.persistence.H2SubscriptionsRepository$CoupleValueType", "target": "io.moquette.broker.Utils" } },{ "group": "nodes", "data": { "id": "69" } },{ "group": "nodes", "data": { "id": "io.moquette.broker.NewNettyAcceptor$3", "parent": "69" } },{ "group": "edges", "data": { "id": "69_118", "source": "69", "target": "118" } },{ "group": "edges", "data": { "id": "69_143", "source": "69", "target": "143" } },{ "group": "edges", "data": { "id": "69_181", "source": "69", "target": "181" } },{ "group": "edges", "data": { "id": "69_101", "source": "69", "target": "101" } },{ "group": "edges", "data": { "id": "69_70", "source": "69", "target": "70" } },{ "group": "edges", "data": { "id": "io.moquette.broker.NewNettyAcceptor$3_io.moquette.broker.NewNettyAcceptor$ByteBufToWebSocketFrameEncoder", "source": "io.moquette.broker.NewNettyAcceptor$3", "target": "io.moquette.broker.NewNettyAcceptor$ByteBufToWebSocketFrameEncoder" } },{ "group": "edges", "data": { "id": "69_39", "source": "69", "target": "39" } },{ "group": "nodes", "data": { "id": "io.moquette.broker.NewNettyAcceptor$ByteBufToWebSocketFrameEncoder", "parent": "69" } },{ "group": "nodes", "data": { "id": "70" } },{ "group": "nodes", "data": { "id": "io.moquette.broker.Authorizator", "parent": "70" } },{ "group": "edges", "data": { "id": "70_187", "source": "70", "target": "187" } },{ "group": "edges", "data": { "id": "70_30", "source": "70", "target": "30" } },{ "group": "edges", "data": { "id": "70_125", "source": "70", "target": "125" } },{ "group": "edges", "data": { "id": "70_31", "source": "70", "target": "31" } },{ "group": "edges", "data": { "id": "70_68", "source": "70", "target": "68" } },{ "group": "edges", "data": { "id": "70_167", "source": "70", "target": "167" } },{ "group": "nodes", "data": { "id": "io.moquette.broker.NewNettyAcceptor$WebSocketFrameToByteBufDecoder", "parent": "70" } },{ "group": "edges", "data": { "id": "70_118", "source": "70", "target": "118" } },{ "group": "nodes", "data": { "id": "71" } },{ "group": "nodes", "data": { "id": "io.moquette.broker.ISessionsRepository$SessionData", "parent": "71" } },{ "group": "edges", "data": { "id": "io.moquette.broker.ISessionsRepository$SessionData_io.moquette.broker.scheduler.Expirable", "source": "io.moquette.broker.ISessionsRepository$SessionData", "target": "io.moquette.broker.scheduler.Expirable" } },{ "group": "edges", "data": { "id": "71_107", "source": "71", "target": "107" } },{ "group": "edges", "data": { "id": "71_139", "source": "71", "target": "139" } },{ "group": "nodes", "data": { "id": "io.moquette.broker.scheduler.Expirable", "parent": "71" } },{ "group": "nodes", "data": { "id": "72" } },{ "group": "nodes", "data": { "id": "io.moquette.persistence.PropertyDataType$MqttPropertyEnum", "parent": "72" } },{ "group": "edges", "data": { "id": "io.moquette.persistence.PropertyDataType$MqttPropertyEnum_io.moquette.persistence.PropertyDataType", "source": "io.moquette.persistence.PropertyDataType$MqttPropertyEnum", "target": "io.moquette.persistence.PropertyDataType" } },{ "group": "nodes", "data": { "id": "io.moquette.persistence.PropertyDataType", "parent": "72" } },{ "group": "edges", "data": { "id": "72_24", "source": "72", "target": "24" } },{ "group": "nodes", "data": { "id": "73" } },{ "group": "nodes", "data": { "id": "io.moquette.broker.DebugUtils", "parent": "73" } },{ "group": "nodes", "data": { "id": "io.moquette.broker.MQTTConnection$2", "parent": "73" } },{ "group": "edges", "data": { "id": "io.moquette.broker.MQTTConnection$2_io.moquette.broker.MQTTConnection", "source": "io.moquette.broker.MQTTConnection$2", "target": "io.moquette.broker.MQTTConnection" } },{ "group": "nodes", "data": { "id": "io.moquette.broker.MQTTConnection", "parent": "73" } },{ "group": "edges", "data": { "id": "73_101", "source": "73", "target": "101" } },{ "group": "edges", "data": { "id": "73_45", "source": "73", "target": "45" } },{ "group": "edges", "data": { "id": "73_167", "source": "73", "target": "167" } },{ "group": "edges", "data": { "id": "io.moquette.broker.MQTTConnection_io.moquette.broker.Quota", "source": "io.moquette.broker.MQTTConnection", "target": "io.moquette.broker.Quota" } },{ "group": "edges", "data": { "id": "io.moquette.broker.MQTTConnection_io.moquette.broker.TopicAliasMapping", "source": "io.moquette.broker.MQTTConnection", "target": "io.moquette.broker.TopicAliasMapping" } },{ "group": "edges", "data": { "id": "73_122", "source": "73", "target": "122" } },{ "group": "edges", "data": { "id": "73_110", "source": "73", "target": "110" } },{ "group": "edges", "data": { "id": "io.moquette.broker.MQTTConnection_io.moquette.broker.SessionCorruptedException", "source": "io.moquette.broker.MQTTConnection", "target": "io.moquette.broker.SessionCorruptedException" } },{ "group": "edges", "data": { "id": "73_125", "source": "73", "target": "125" } },{ "group": "edges", "data": { "id": "73_144", "source": "73", "target": "144" } },{ "group": "edges", "data": { "id": "73_143", "source": "73", "target": "143" } },{ "group": "edges", "data": { "id": "73_21", "source": "73", "target": "21" } },{ "group": "edges", "data": { "id": "73_26", "source": "73", "target": "26" } },{ "group": "edges", "data": { "id": "73_137", "source": "73", "target": "137" } },{ "group": "edges", "data": { "id": "73_68", "source": "73", "target": "68" } },{ "group": "edges", "data": { "id": "io.moquette.broker.MQTTConnection_io.moquette.broker.DebugUtils", "source": "io.moquette.broker.MQTTConnection", "target": "io.moquette.broker.DebugUtils" } },{ "group": "edges", "data": { "id": "73_79", "source": "73", "target": "79" } },{ "group": "nodes", "data": { "id": "io.moquette.broker.Quota", "parent": "73" } },{ "group": "nodes", "data": { "id": "io.moquette.broker.SessionCorruptedException", "parent": "73" } },{ "group": "nodes", "data": { "id": "io.moquette.broker.TopicAliasMapping", "parent": "73" } },{ "group": "nodes", "data": { "id": "74" } },{ "group": "nodes", "data": { "id": "io.moquette.broker.metrics.BytesMetrics", "parent": "74" } },{ "group": "nodes", "data": { "id": "io.moquette.broker.metrics.BytesMetricsCollector", "parent": "74" } },{ "group": "edges", "data": { "id": "io.moquette.broker.metrics.BytesMetricsCollector_io.moquette.broker.metrics.BytesMetrics", "source": "io.moquette.broker.metrics.BytesMetricsCollector", "target": "io.moquette.broker.metrics.BytesMetrics" } },{ "group": "nodes", "data": { "id": "79" } },{ "group": "nodes", "data": { "id": "io.moquette.broker.PostOffice$ExpirableTopic", "parent": "79" } },{ "group": "edges", "data": { "id": "79_71", "source": "79", "target": "71" } },{ "group": "edges", "data": { "id": "79_125", "source": "79", "target": "125" } },{ "group": "edges", "data": { "id": "79_167", "source": "79", "target": "167" } },{ "group": "nodes", "data": { "id": "io.moquette.broker.RoutingResults", "parent": "79" } },{ "group": "nodes", "data": { "id": "85" } },{ "group": "nodes", "data": { "id": "io.moquette.broker.config.FluentConfig$TLSConfig", "parent": "85" } },{ "group": "edges", "data": { "id": "85_6", "source": "85", "target": "6" } },{ "group": "edges", "data": { "id": "85_25", "source": "85", "target": "25" } },{ "group": "nodes", "data": { "id": "86" } },{ "group": "nodes", "data": { "id": "io.moquette.broker.config.FluentConfig$BufferFlushKind", "parent": "86" } },{ "group": "nodes", "data": { "id": "87" } },{ "group": "nodes", "data": { "id": "io.moquette.broker.IRetainedRepository", "parent": "87" } },{ "group": "edges", "data": { "id": "87_125", "source": "87", "target": "125" } },{ "group": "edges", "data": { "id": "io.moquette.broker.IRetainedRepository_io.moquette.broker.RetainedMessage", "source": "io.moquette.broker.IRetainedRepository", "target": "io.moquette.broker.RetainedMessage" } },{ "group": "nodes", "data": { "id": "io.moquette.broker.MemoryRetainedRepository", "parent": "87" } },{ "group": "edges", "data": { "id": "io.moquette.broker.MemoryRetainedRepository_io.moquette.broker.IRetainedRepository", "source": "io.moquette.broker.MemoryRetainedRepository", "target": "io.moquette.broker.IRetainedRepository" } },{ "group": "edges", "data": { "id": "io.moquette.broker.MemoryRetainedRepository_io.moquette.broker.RetainedMessage", "source": "io.moquette.broker.MemoryRetainedRepository", "target": "io.moquette.broker.RetainedMessage" } },{ "group": "nodes", "data": { "id": "io.moquette.broker.RetainedMessage", "parent": "87" } },{ "group": "nodes", "data": { "id": "88" } },{ "group": "nodes", "data": { "id": "io.moquette.broker.subscriptions.ISubscriptionsDirectory", "parent": "88" } },{ "group": "edges", "data": { "id": "88_194", "source": "88", "target": "194" } },{ "group": "edges", "data": { "id": "88_125", "source": "88", "target": "125" } },{ "group": "edges", "data": { "id": "88_173", "source": "88", "target": "173" } },{ "group": "edges", "data": { "id": "88_167", "source": "88", "target": "167" } },{ "group": "edges", "data": { "id": "88_157", "source": "88", "target": "157" } },{ "group": "nodes", "data": { "id": "91" } },{ "group": "nodes", "data": { "id": "io.moquette.broker.metrics.MQTTMessageLogger$1", "parent": "91" } },{ "group": "edges", "data": { "id": "io.moquette.broker.metrics.MQTTMessageLogger$1_io.moquette.broker.metrics.MQTTMessageLogger", "source": "io.moquette.broker.metrics.MQTTMessageLogger$1", "target": "io.moquette.broker.metrics.MQTTMessageLogger" } },{ "group": "nodes", "data": { "id": "io.moquette.broker.metrics.MQTTMessageLogger", "parent": "91" } },{ "group": "edges", "data": { "id": "91_143", "source": "91", "target": "143" } },{ "group": "edges", "data": { "id": "91_68", "source": "91", "target": "68" } },{ "group": "nodes", "data": { "id": "96" } },{ "group": "nodes", "data": { "id": "io.moquette.broker.scheduler.ExpirableTracker", "parent": "96" } },{ "group": "edges", "data": { "id": "96_71", "source": "96", "target": "71" } },{ "group": "nodes", "data": { "id": "98" } },{ "group": "nodes", "data": { "id": "io.moquette.broker.subscriptions.CTrie$Action", "parent": "98" } },{ "group": "edges", "data": { "id": "io.moquette.broker.subscriptions.CTrie$Action_io.moquette.broker.subscriptions.CTrie", "source": "io.moquette.broker.subscriptions.CTrie$Action", "target": "io.moquette.broker.subscriptions.CTrie" } },{ "group": "nodes", "data": { "id": "io.moquette.broker.subscriptions.CTrie", "parent": "98" } },{ "group": "edges", "data": { "id": "98_137", "source": "98", "target": "137" } },{ "group": "edges", "data": { "id": "98_190", "source": "98", "target": "190" } },{ "group": "edges", "data": { "id": "98_125", "source": "98", "target": "125" } },{ "group": "edges", "data": { "id": "98_174", "source": "98", "target": "174" } },{ "group": "edges", "data": { "id": "98_173", "source": "98", "target": "173" } },{ "group": "edges", "data": { "id": "98_100", "source": "98", "target": "100" } },{ "group": "edges", "data": { "id": "98_157", "source": "98", "target": "157" } },{ "group": "edges", "data": { "id": "98_117", "source": "98", "target": "117" } },{ "group": "nodes", "data": { "id": "99" } },{ "group": "nodes", "data": { "id": "io.moquette.broker.metrics.MessageMetrics", "parent": "99" } },{ "group": "nodes", "data": { "id": "io.moquette.broker.metrics.MessageMetricsHandler", "parent": "99" } },{ "group": "edges", "data": { "id": "io.moquette.broker.metrics.MessageMetricsHandler_io.moquette.broker.metrics.MessageMetrics", "source": "io.moquette.broker.metrics.MessageMetricsHandler", "target": "io.moquette.broker.metrics.MessageMetrics" } },{ "group": "nodes", "data": { "id": "100" } },{ "group": "nodes", "data": { "id": "io.moquette.broker.subscriptions.CTrie$SubscriptionRequest", "parent": "100" } },{ "group": "edges", "data": { "id": "100_125", "source": "100", "target": "125" } },{ "group": "edges", "data": { "id": "100_157", "source": "100", "target": "157" } },{ "group": "edges", "data": { "id": "100_167", "source": "100", "target": "167" } },{ "group": "edges", "data": { "id": "100_173", "source": "100", "target": "173" } },{ "group": "edges", "data": { "id": "100_146", "source": "100", "target": "146" } },{ "group": "edges", "data": { "id": "100_137", "source": "100", "target": "137" } },{ "group": "nodes", "data": { "id": "101" } },{ "group": "nodes", "data": { "id": "io.moquette.broker.BrokerConfiguration", "parent": "101" } },{ "group": "edges", "data": { "id": "101_144", "source": "101", "target": "144" } },{ "group": "nodes", "data": { "id": "io.moquette.broker.NewNettyAcceptor$1", "parent": "101" } },{ "group": "edges", "data": { "id": "101_118", "source": "101", "target": "118" } },{ "group": "nodes", "data": { "id": "io.moquette.broker.NewNettyAcceptor$2", "parent": "101" } },{ "group": "edges", "data": { "id": "101_143", "source": "101", "target": "143" } },{ "group": "edges", "data": { "id": "101_181", "source": "101", "target": "181" } },{ "group": "edges", "data": { "id": "io.moquette.broker.NewNettyAcceptor$2_io.moquette.broker.NewNettyAcceptor$1", "source": "io.moquette.broker.NewNettyAcceptor$2", "target": "io.moquette.broker.NewNettyAcceptor$1" } },{ "group": "edges", "data": { "id": "io.moquette.broker.NewNettyAcceptor$2_io.moquette.broker.BrokerConfiguration", "source": "io.moquette.broker.NewNettyAcceptor$2", "target": "io.moquette.broker.BrokerConfiguration" } },{ "group": "nodes", "data": { "id": "106" } },{ "group": "nodes", "data": { "id": "io.moquette.broker.metrics.BytesMetricsHandler", "parent": "106" } },{ "group": "edges", "data": { "id": "106_74", "source": "106", "target": "74" } },{ "group": "nodes", "data": { "id": "107" } },{ "group": "nodes", "data": { "id": "io.moquette.broker.ISessionsRepository$Will", "parent": "107" } },{ "group": "edges", "data": { "id": "107_185", "source": "107", "target": "185" } },{ "group": "edges", "data": { "id": "107_139", "source": "107", "target": "139" } },{ "group": "nodes", "data": { "id": "109" } },{ "group": "nodes", "data": { "id": "io.moquette.broker.config.FileResourceLoader", "parent": "109" } },{ "group": "edges", "data": { "id": "io.moquette.broker.config.FileResourceLoader_io.moquette.broker.config.IResourceLoader", "source": "io.moquette.broker.config.FileResourceLoader", "target": "io.moquette.broker.config.IResourceLoader" } },{ "group": "nodes", "data": { "id": "io.moquette.broker.config.IResourceLoader", "parent": "109" } },{ "group": "nodes", "data": { "id": "io.moquette.broker.config.ResourceLoaderConfig", "parent": "109" } },{ "group": "edges", "data": { "id": "io.moquette.broker.config.ResourceLoaderConfig_io.moquette.broker.config.IResourceLoader", "source": "io.moquette.broker.config.ResourceLoaderConfig", "target": "io.moquette.broker.config.IResourceLoader" } },{ "group": "nodes", "data": { "id": "110" } },{ "group": "nodes", "data": { "id": "io.moquette.broker.MQTTConnection$1", "parent": "110" } },{ "group": "edges", "data": { "id": "io.moquette.broker.MQTTConnection$1_io.moquette.broker.SessionRegistry$SessionCreationResult", "source": "io.moquette.broker.MQTTConnection$1", "target": "io.moquette.broker.SessionRegistry$SessionCreationResult" } },{ "group": "edges", "data": { "id": "110_60", "source": "110", "target": "60" } },{ "group": "edges", "data": { "id": "110_167", "source": "110", "target": "167" } },{ "group": "edges", "data": { "id": "110_122", "source": "110", "target": "122" } },{ "group": "nodes", "data": { "id": "io.moquette.broker.SessionRegistry$SessionCreationResult", "parent": "110" } },{ "group": "nodes", "data": { "id": "111" } },{ "group": "nodes", "data": { "id": "io.moquette.broker.config.ClasspathResourceLoader", "parent": "111" } },{ "group": "edges", "data": { "id": "111_109", "source": "111", "target": "109" } },{ "group": "edges", "data": { "id": "111_39", "source": "111", "target": "39" } },{ "group": "nodes", "data": { "id": "112" } },{ "group": "nodes", "data": { "id": "io.moquette.broker.SessionRegistry$EnqueuedMessage", "parent": "112" } },{ "group": "nodes", "data": { "id": "113" } },{ "group": "nodes", "data": { "id": "io.moquette.broker.config.MemoryConfig", "parent": "113" } },{ "group": "edges", "data": { "id": "113_39", "source": "113", "target": "39" } },{ "group": "edges", "data": { "id": "113_109", "source": "113", "target": "109" } },{ "group": "nodes", "data": { "id": "116" } },{ "group": "nodes", "data": { "id": "io.moquette.broker.unsafequeues.QueueException", "parent": "116" } },{ "group": "nodes", "data": { "id": "io.moquette.persistence.SegmentPersistentQueue", "parent": "116" } },{ "group": "edges", "data": { "id": "116_129", "source": "116", "target": "129" } },{ "group": "edges", "data": { "id": "116_159", "source": "116", "target": "159" } },{ "group": "edges", "data": { "id": "116_112", "source": "116", "target": "112" } },{ "group": "edges", "data": { "id": "io.moquette.persistence.SegmentPersistentQueue_io.moquette.broker.unsafequeues.QueueException", "source": "io.moquette.persistence.SegmentPersistentQueue", "target": "io.moquette.broker.unsafequeues.QueueException" } },{ "group": "edges", "data": { "id": "116_9", "source": "116", "target": "9" } },{ "group": "nodes", "data": { "id": "117" } },{ "group": "nodes", "data": { "id": "io.moquette.broker.subscriptions.CTrie$IVisitor", "parent": "117" } },{ "group": "edges", "data": { "id": "117_190", "source": "117", "target": "190" } },{ "group": "nodes", "data": { "id": "io.moquette.broker.subscriptions.SubscriptionCounterVisitor", "parent": "117" } },{ "group": "edges", "data": { "id": "io.moquette.broker.subscriptions.SubscriptionCounterVisitor_io.moquette.broker.subscriptions.CTrie$IVisitor", "source": "io.moquette.broker.subscriptions.SubscriptionCounterVisitor", "target": "io.moquette.broker.subscriptions.CTrie$IVisitor" } },{ "group": "nodes", "data": { "id": "118" } },{ "group": "nodes", "data": { "id": "io.moquette.broker.NewNettyAcceptor$LocalPortReaderFutureListener", "parent": "118" } },{ "group": "edges", "data": { "id": "io.moquette.broker.NewNettyAcceptor$LocalPortReaderFutureListener_io.moquette.broker.NewNettyAcceptor", "source": "io.moquette.broker.NewNettyAcceptor$LocalPortReaderFutureListener", "target": "io.moquette.broker.NewNettyAcceptor" } },{ "group": "nodes", "data": { "id": "io.moquette.broker.NewNettyAcceptor$PipelineInitializer", "parent": "118" } },{ "group": "edges", "data": { "id": "io.moquette.broker.NewNettyAcceptor$PipelineInitializer_io.moquette.broker.NewNettyAcceptor", "source": "io.moquette.broker.NewNettyAcceptor$PipelineInitializer", "target": "io.moquette.broker.NewNettyAcceptor" } },{ "group": "nodes", "data": { "id": "io.moquette.broker.NewNettyAcceptor", "parent": "118" } },{ "group": "edges", "data": { "id": "118_74", "source": "118", "target": "74" } },{ "group": "edges", "data": { "id": "118_43", "source": "118", "target": "43" } },{ "group": "edges", "data": { "id": "118_181", "source": "118", "target": "181" } },{ "group": "edges", "data": { "id": "118_198", "source": "118", "target": "198" } },{ "group": "edges", "data": { "id": "118_143", "source": "118", "target": "143" } },{ "group": "edges", "data": { "id": "118_99", "source": "118", "target": "99" } },{ "group": "edges", "data": { "id": "118_144", "source": "118", "target": "144" } },{ "group": "edges", "data": { "id": "118_106", "source": "118", "target": "106" } },{ "group": "edges", "data": { "id": "118_4", "source": "118", "target": "4" } },{ "group": "edges", "data": { "id": "118_91", "source": "118", "target": "91" } },{ "group": "nodes", "data": { "id": "119" } },{ "group": "nodes", "data": { "id": "io.moquette.broker.security.ResourceAuthenticator", "parent": "119" } },{ "group": "edges", "data": { "id": "119_45", "source": "119", "target": "45" } },{ "group": "edges", "data": { "id": "119_109", "source": "119", "target": "109" } },{ "group": "edges", "data": { "id": "119_12", "source": "119", "target": "12" } },{ "group": "nodes", "data": { "id": "122" } },{ "group": "nodes", "data": { "id": "io.moquette.broker.PostOffice$BatchingPublishesCollector", "parent": "122" } },{ "group": "edges", "data": { "id": "122_173", "source": "122", "target": "173" } },{ "group": "edges", "data": { "id": "122_171", "source": "122", "target": "171" } },{ "group": "edges", "data": { "id": "122_167", "source": "122", "target": "167" } },{ "group": "edges", "data": { "id": "io.moquette.broker.PostOffice$BatchingPublishesCollector_io.moquette.broker.PostOffice$RouteResult", "source": "io.moquette.broker.PostOffice$BatchingPublishesCollector", "target": "io.moquette.broker.PostOffice$RouteResult" } },{ "group": "nodes", "data": { "id": "io.moquette.broker.PostOffice$RouteResult", "parent": "122" } },{ "group": "nodes", "data": { "id": "124" } },{ "group": "nodes", "data": { "id": "io.moquette.interception.BrokerInterceptor", "parent": "124" } },{ "group": "edges", "data": { "id": "124_39", "source": "124", "target": "39" } },{ "group": "edges", "data": { "id": "124_173", "source": "124", "target": "173" } },{ "group": "edges", "data": { "id": "io.moquette.interception.BrokerInterceptor_io.moquette.interception.messages.InterceptAcknowledgedMessage", "source": "io.moquette.interception.BrokerInterceptor", "target": "io.moquette.interception.messages.InterceptAcknowledgedMessage" } },{ "group": "edges", "data": { "id": "124_144", "source": "124", "target": "144" } },{ "group": "edges", "data": { "id": "124_32", "source": "124", "target": "32" } },{ "group": "edges", "data": { "id": "124_168", "source": "124", "target": "168" } },{ "group": "edges", "data": { "id": "124_68", "source": "124", "target": "68" } },{ "group": "edges", "data": { "id": "124_125", "source": "124", "target": "125" } },{ "group": "edges", "data": { "id": "124_169", "source": "124", "target": "169" } },{ "group": "nodes", "data": { "id": "io.moquette.interception.messages.InterceptAcknowledgedMessage", "parent": "124" } },{ "group": "nodes", "data": { "id": "125" } },{ "group": "nodes", "data": { "id": "io.moquette.broker.security.DenyAllAuthorizatorPolicy", "parent": "125" } },{ "group": "edges", "data": { "id": "125_187", "source": "125", "target": "187" } },{ "group": "edges", "data": { "id": "io.moquette.broker.security.DenyAllAuthorizatorPolicy_io.moquette.broker.subscriptions.Topic", "source": "io.moquette.broker.security.DenyAllAuthorizatorPolicy", "target": "io.moquette.broker.subscriptions.Topic" } },{ "group": "nodes", "data": { "id": "io.moquette.broker.subscriptions.Topic", "parent": "125" } },{ "group": "edges", "data": { "id": "125_137", "source": "125", "target": "137" } },{ "group": "nodes", "data": { "id": "129" } },{ "group": "nodes", "data": { "id": "io.moquette.broker.AbstractSessionMessageQueue", "parent": "129" } },{ "group": "edges", "data": { "id": "129_175", "source": "129", "target": "175" } },{ "group": "nodes", "data": { "id": "io.moquette.broker.InMemoryQueue", "parent": "129" } },{ "group": "edges", "data": { "id": "io.moquette.broker.InMemoryQueue_io.moquette.broker.AbstractSessionMessageQueue", "source": "io.moquette.broker.InMemoryQueue", "target": "io.moquette.broker.AbstractSessionMessageQueue" } },{ "group": "edges", "data": { "id": "129_144", "source": "129", "target": "144" } },{ "group": "edges", "data": { "id": "129_112", "source": "129", "target": "112" } },{ "group": "edges", "data": { "id": "129_68", "source": "129", "target": "68" } },{ "group": "nodes", "data": { "id": "io.moquette.persistence.H2PersistentQueue", "parent": "129" } },{ "group": "edges", "data": { "id": "io.moquette.persistence.H2PersistentQueue_io.moquette.broker.AbstractSessionMessageQueue", "source": "io.moquette.persistence.H2PersistentQueue", "target": "io.moquette.broker.AbstractSessionMessageQueue" } },{ "group": "edges", "data": { "id": "129_195", "source": "129", "target": "195" } },{ "group": "nodes", "data": { "id": "132" } },{ "group": "nodes", "data": { "id": "io.moquette.persistence.H2RetainedRepository$RetainedMessageValueType", "parent": "132" } },{ "group": "edges", "data": { "id": "io.moquette.persistence.H2RetainedRepository$RetainedMessageValueType_io.moquette.persistence.PropertiesDataType", "source": "io.moquette.persistence.H2RetainedRepository$RetainedMessageValueType", "target": "io.moquette.persistence.PropertiesDataType" } },{ "group": "edges", "data": { "id": "132_87", "source": "132", "target": "87" } },{ "group": "edges", "data": { "id": "132_203", "source": "132", "target": "203" } },{ "group": "edges", "data": { "id": "132_125", "source": "132", "target": "125" } },{ "group": "edges", "data": { "id": "io.moquette.persistence.H2RetainedRepository$RetainedMessageValueType_io.moquette.persistence.H2RetainedRepository", "source": "io.moquette.persistence.H2RetainedRepository$RetainedMessageValueType", "target": "io.moquette.persistence.H2RetainedRepository" } },{ "group": "nodes", "data": { "id": "io.moquette.persistence.H2RetainedRepository", "parent": "132" } },{ "group": "nodes", "data": { "id": "io.moquette.persistence.PropertiesDataType", "parent": "132" } },{ "group": "edges", "data": { "id": "132_72", "source": "132", "target": "72" } },{ "group": "edges", "data": { "id": "132_14", "source": "132", "target": "14" } },{ "group": "nodes", "data": { "id": "137" } },{ "group": "nodes", "data": { "id": "io.moquette.broker.subscriptions.DumpTreeVisitor", "parent": "137" } },{ "group": "edges", "data": { "id": "137_117", "source": "137", "target": "117" } },{ "group": "edges", "data": { "id": "137_190", "source": "137", "target": "190" } },{ "group": "edges", "data": { "id": "137_173", "source": "137", "target": "173" } },{ "group": "edges", "data": { "id": "io.moquette.broker.subscriptions.DumpTreeVisitor_io.moquette.broker.subscriptions.Token", "source": "io.moquette.broker.subscriptions.DumpTreeVisitor", "target": "io.moquette.broker.subscriptions.Token" } },{ "group": "nodes", "data": { "id": "io.moquette.broker.subscriptions.Token", "parent": "137" } },{ "group": "nodes", "data": { "id": "139" } },{ "group": "nodes", "data": { "id": "io.moquette.broker.ISessionsRepository", "parent": "139" } },{ "group": "edges", "data": { "id": "139_185", "source": "139", "target": "185" } },{ "group": "nodes", "data": { "id": "io.moquette.persistence.MemorySessionsRepository", "parent": "139" } },{ "group": "edges", "data": { "id": "io.moquette.persistence.MemorySessionsRepository_io.moquette.broker.ISessionsRepository", "source": "io.moquette.persistence.MemorySessionsRepository", "target": "io.moquette.broker.ISessionsRepository" } },{ "group": "nodes", "data": { "id": "141" } },{ "group": "nodes", "data": { "id": "io.moquette.broker.unsafequeues.Segment", "parent": "141" } },{ "group": "edges", "data": { "id": "io.moquette.broker.unsafequeues.Segment_io.moquette.broker.unsafequeues.SegmentPointer", "source": "io.moquette.broker.unsafequeues.Segment", "target": "io.moquette.broker.unsafequeues.SegmentPointer" } },{ "group": "edges", "data": { "id": "io.moquette.broker.unsafequeues.Segment_io.moquette.broker.unsafequeues.VirtualPointer", "source": "io.moquette.broker.unsafequeues.Segment", "target": "io.moquette.broker.unsafequeues.VirtualPointer" } },{ "group": "nodes", "data": { "id": "io.moquette.broker.unsafequeues.SegmentPointer", "parent": "141" } },{ "group": "nodes", "data": { "id": "io.moquette.broker.unsafequeues.VirtualPointer", "parent": "141" } },{ "group": "nodes", "data": { "id": "143" } },{ "group": "nodes", "data": { "id": "io.moquette.broker.MoquetteIdleTimeoutHandler", "parent": "143" } },{ "group": "edges", "data": { "id": "io.moquette.broker.MoquetteIdleTimeoutHandler_io.moquette.broker.NettyUtils", "source": "io.moquette.broker.MoquetteIdleTimeoutHandler", "target": "io.moquette.broker.NettyUtils" } },{ "group": "nodes", "data": { "id": "io.moquette.broker.NettyUtils", "parent": "143" } },{ "group": "nodes", "data": { "id": "144" } },{ "group": "nodes", "data": { "id": "io.moquette.BrokerConstants", "parent": "144" } },{ "group": "nodes", "data": { "id": "io.moquette.broker.MQTTConnectionFactory", "parent": "144" } },{ "group": "edges", "data": { "id": "144_9", "source": "144", "target": "9" } },{ "group": "edges", "data": { "id": "144_167", "source": "144", "target": "167" } },{ "group": "nodes", "data": { "id": "io.moquette.broker.MemoryQueueRepository", "parent": "144" } },{ "group": "edges", "data": { "id": "144_200", "source": "144", "target": "200" } },{ "group": "edges", "data": { "id": "144_175", "source": "144", "target": "175" } },{ "group": "edges", "data": { "id": "144_112", "source": "144", "target": "112" } },{ "group": "nodes", "data": { "id": "io.moquette.broker.Server", "parent": "144" } },{ "group": "edges", "data": { "id": "144_109", "source": "144", "target": "109" } },{ "group": "edges", "data": { "id": "144_29", "source": "144", "target": "29" } },{ "group": "edges", "data": { "id": "144_198", "source": "144", "target": "198" } },{ "group": "edges", "data": { "id": "144_187", "source": "144", "target": "187" } },{ "group": "edges", "data": { "id": "144_139", "source": "144", "target": "139" } },{ "group": "edges", "data": { "id": "144_194", "source": "144", "target": "194" } },{ "group": "edges", "data": { "id": "144_87", "source": "144", "target": "87" } },{ "group": "edges", "data": { "id": "144_88", "source": "144", "target": "88" } },{ "group": "edges", "data": { "id": "144_70", "source": "144", "target": "70" } },{ "group": "edges", "data": { "id": "144_171", "source": "144", "target": "171" } },{ "group": "edges", "data": { "id": "io.moquette.broker.Server_io.moquette.broker.MQTTConnectionFactory", "source": "io.moquette.broker.Server", "target": "io.moquette.broker.MQTTConnectionFactory" } },{ "group": "edges", "data": { "id": "144_181", "source": "144", "target": "181" } },{ "group": "edges", "data": { "id": "144_116", "source": "144", "target": "116" } },{ "group": "edges", "data": { "id": "144_79", "source": "144", "target": "79" } },{ "group": "edges", "data": { "id": "144_162", "source": "144", "target": "162" } },{ "group": "edges", "data": { "id": "144_113", "source": "144", "target": "113" } },{ "group": "edges", "data": { "id": "io.moquette.broker.Server_io.moquette.BrokerConstants", "source": "io.moquette.broker.Server", "target": "io.moquette.BrokerConstants" } },{ "group": "edges", "data": { "id": "144_164", "source": "144", "target": "164" } },{ "group": "edges", "data": { "id": "144_30", "source": "144", "target": "30" } },{ "group": "edges", "data": { "id": "io.moquette.broker.Server_io.moquette.broker.MemoryQueueRepository", "source": "io.moquette.broker.Server", "target": "io.moquette.broker.MemoryQueueRepository" } },{ "group": "edges", "data": { "id": "io.moquette.broker.Server_io.moquette.persistence.SegmentQueueRepository", "source": "io.moquette.broker.Server", "target": "io.moquette.persistence.SegmentQueueRepository" } },{ "group": "edges", "data": { "id": "144_125", "source": "144", "target": "125" } },{ "group": "edges", "data": { "id": "144_5", "source": "144", "target": "5" } },{ "group": "edges", "data": { "id": "144_176", "source": "144", "target": "176" } },{ "group": "edges", "data": { "id": "144_119", "source": "144", "target": "119" } },{ "group": "edges", "data": { "id": "144_68", "source": "144", "target": "68" } },{ "group": "nodes", "data": { "id": "io.moquette.persistence.SegmentQueueRepository", "parent": "144" } },{ "group": "edges", "data": { "id": "144_149", "source": "144", "target": "149" } },{ "group": "edges", "data": { "id": "144_36", "source": "144", "target": "36" } },{ "group": "nodes", "data": { "id": "146" } },{ "group": "nodes", "data": { "id": "io.moquette.broker.subscriptions.SharedSubscription", "parent": "146" } },{ "group": "edges", "data": { "id": "146_157", "source": "146", "target": "157" } },{ "group": "edges", "data": { "id": "146_125", "source": "146", "target": "125" } },{ "group": "edges", "data": { "id": "146_167", "source": "146", "target": "167" } },{ "group": "edges", "data": { "id": "146_173", "source": "146", "target": "173" } },{ "group": "nodes", "data": { "id": "147" } },{ "group": "nodes", "data": { "id": "io.moquette.broker.unsafequeues.QueuePool$1", "parent": "147" } },{ "group": "edges", "data": { "id": "147_149", "source": "147", "target": "149" } },{ "group": "nodes", "data": { "id": "io.moquette.broker.unsafequeues.QueuePool$QueueName", "parent": "147" } },{ "group": "edges", "data": { "id": "io.moquette.broker.unsafequeues.QueuePool$QueueName_io.moquette.broker.unsafequeues.QueuePool$1", "source": "io.moquette.broker.unsafequeues.QueuePool$QueueName", "target": "io.moquette.broker.unsafequeues.QueuePool$1" } },{ "group": "nodes", "data": { "id": "149" } },{ "group": "nodes", "data": { "id": "io.moquette.broker.unsafequeues.QueuePool$SegmentRef", "parent": "149" } },{ "group": "edges", "data": { "id": "149_141", "source": "149", "target": "141" } },{ "group": "edges", "data": { "id": "io.moquette.broker.unsafequeues.QueuePool$SegmentRef_io.moquette.broker.unsafequeues.QueuePool", "source": "io.moquette.broker.unsafequeues.QueuePool$SegmentRef", "target": "io.moquette.broker.unsafequeues.QueuePool" } },{ "group": "nodes", "data": { "id": "io.moquette.broker.unsafequeues.QueuePool", "parent": "149" } },{ "group": "edges", "data": { "id": "149_5", "source": "149", "target": "5" } },{ "group": "edges", "data": { "id": "149_116", "source": "149", "target": "116" } },{ "group": "edges", "data": { "id": "149_10", "source": "149", "target": "10" } },{ "group": "nodes", "data": { "id": "152" } },{ "group": "nodes", "data": { "id": "io.moquette.broker.SessionRegistry$PublishedMessage", "parent": "152" } },{ "group": "edges", "data": { "id": "152_112", "source": "152", "target": "112" } },{ "group": "edges", "data": { "id": "152_125", "source": "152", "target": "125" } },{ "group": "nodes", "data": { "id": "157" } },{ "group": "nodes", "data": { "id": "io.moquette.broker.subscriptions.CTrie$UnsubscribeRequest", "parent": "157" } },{ "group": "edges", "data": { "id": "157_125", "source": "157", "target": "125" } },{ "group": "edges", "data": { "id": "io.moquette.broker.subscriptions.CTrie$UnsubscribeRequest_io.moquette.broker.subscriptions.ShareName", "source": "io.moquette.broker.subscriptions.CTrie$UnsubscribeRequest", "target": "io.moquette.broker.subscriptions.ShareName" } },{ "group": "edges", "data": { "id": "157_137", "source": "157", "target": "137" } },{ "group": "nodes", "data": { "id": "io.moquette.broker.subscriptions.ShareName", "parent": "157" } },{ "group": "nodes", "data": { "id": "159" } },{ "group": "nodes", "data": { "id": "io.moquette.persistence.SegmentedPersistentQueueSerDes$MessageType", "parent": "159" } },{ "group": "edges", "data": { "id": "io.moquette.persistence.SegmentedPersistentQueueSerDes$MessageType_io.moquette.persistence.SegmentedPersistentQueueSerDes", "source": "io.moquette.persistence.SegmentedPersistentQueueSerDes$MessageType", "target": "io.moquette.persistence.SegmentedPersistentQueueSerDes" } },{ "group": "nodes", "data": { "id": "io.moquette.persistence.SegmentedPersistentQueueSerDes", "parent": "159" } },{ "group": "edges", "data": { "id": "159_112", "source": "159", "target": "112" } },{ "group": "edges", "data": { "id": "159_152", "source": "159", "target": "152" } },{ "group": "edges", "data": { "id": "159_72", "source": "159", "target": "72" } },{ "group": "edges", "data": { "id": "159_125", "source": "159", "target": "125" } },{ "group": "edges", "data": { "id": "159_195", "source": "159", "target": "195" } },{ "group": "edges", "data": { "id": "159_9", "source": "159", "target": "9" } },{ "group": "edges", "data": { "id": "159_68", "source": "159", "target": "68" } },{ "group": "edges", "data": { "id": "159_14", "source": "159", "target": "14" } },{ "group": "nodes", "data": { "id": "162" } },{ "group": "nodes", "data": { "id": "io.moquette.broker.ClientDescriptor", "parent": "162" } },{ "group": "nodes", "data": { "id": "164" } },{ "group": "nodes", "data": { "id": "io.moquette.broker.DefaultMoquetteSslContextCreator$1", "parent": "164" } },{ "group": "edges", "data": { "id": "io.moquette.broker.DefaultMoquetteSslContextCreator$1_io.moquette.broker.DefaultMoquetteSslContextCreator", "source": "io.moquette.broker.DefaultMoquetteSslContextCreator$1", "target": "io.moquette.broker.DefaultMoquetteSslContextCreator" } },{ "group": "nodes", "data": { "id": "io.moquette.broker.DefaultMoquetteSslContextCreator", "parent": "164" } },{ "group": "edges", "data": { "id": "164_198", "source": "164", "target": "198" } },{ "group": "edges", "data": { "id": "164_39", "source": "164", "target": "39" } },{ "group": "nodes", "data": { "id": "165" } },{ "group": "nodes", "data": { "id": "io.moquette.broker.security.Authorization$Permission", "parent": "165" } },{ "group": "edges", "data": { "id": "io.moquette.broker.security.Authorization$Permission_io.moquette.broker.security.Authorization", "source": "io.moquette.broker.security.Authorization$Permission", "target": "io.moquette.broker.security.Authorization" } },{ "group": "nodes", "data": { "id": "io.moquette.broker.security.Authorization", "parent": "165" } },{ "group": "edges", "data": { "id": "165_125", "source": "165", "target": "125" } },{ "group": "nodes", "data": { "id": "166" } },{ "group": "nodes", "data": { "id": "io.moquette.broker.security.DeclarativeAuthorizatorPolicy$Builder", "parent": "166" } },{ "group": "edges", "data": { "id": "io.moquette.broker.security.DeclarativeAuthorizatorPolicy$Builder_io.moquette.broker.security.DeclarativeAuthorizatorPolicy", "source": "io.moquette.broker.security.DeclarativeAuthorizatorPolicy$Builder", "target": "io.moquette.broker.security.DeclarativeAuthorizatorPolicy" } },{ "group": "edges", "data": { "id": "166_125", "source": "166", "target": "125" } },{ "group": "edges", "data": { "id": "166_187", "source": "166", "target": "187" } },{ "group": "nodes", "data": { "id": "io.moquette.broker.security.DeclarativeAuthorizatorPolicy$TopicUserClient", "parent": "166" } },{ "group": "edges", "data": { "id": "io.moquette.broker.security.DeclarativeAuthorizatorPolicy$TopicUserClient_io.moquette.broker.security.DeclarativeAuthorizatorPolicy", "source": "io.moquette.broker.security.DeclarativeAuthorizatorPolicy$TopicUserClient", "target": "io.moquette.broker.security.DeclarativeAuthorizatorPolicy" } },{ "group": "nodes", "data": { "id": "io.moquette.broker.security.DeclarativeAuthorizatorPolicy", "parent": "166" } },{ "group": "nodes", "data": { "id": "167" } },{ "group": "nodes", "data": { "id": "io.moquette.broker.PostOffice$1", "parent": "167" } },{ "group": "edges", "data": { "id": "io.moquette.broker.PostOffice$1_io.moquette.broker.PostOffice", "source": "io.moquette.broker.PostOffice$1", "target": "io.moquette.broker.PostOffice" } },{ "group": "nodes", "data": { "id": "io.moquette.broker.PostOffice$RouteResult$Status", "parent": "167" } },{ "group": "edges", "data": { "id": "io.moquette.broker.PostOffice$RouteResult$Status_io.moquette.broker.PostOffice", "source": "io.moquette.broker.PostOffice$RouteResult$Status", "target": "io.moquette.broker.PostOffice" } },{ "group": "nodes", "data": { "id": "io.moquette.broker.PostOffice", "parent": "167" } },{ "group": "edges", "data": { "id": "167_87", "source": "167", "target": "87" } },{ "group": "edges", "data": { "id": "167_139", "source": "167", "target": "139" } },{ "group": "edges", "data": { "id": "167_124", "source": "167", "target": "124" } },{ "group": "edges", "data": { "id": "167_171", "source": "167", "target": "171" } },{ "group": "edges", "data": { "id": "167_34", "source": "167", "target": "34" } },{ "group": "edges", "data": { "id": "167_107", "source": "167", "target": "107" } },{ "group": "edges", "data": { "id": "167_60", "source": "167", "target": "60" } },{ "group": "edges", "data": { "id": "167_173", "source": "167", "target": "173" } },{ "group": "edges", "data": { "id": "io.moquette.broker.PostOffice_io.moquette.broker.subscriptions.SubscriptionIdentifier", "source": "io.moquette.broker.PostOffice", "target": "io.moquette.broker.subscriptions.SubscriptionIdentifier" } },{ "group": "edges", "data": { "id": "167_157", "source": "167", "target": "157" } },{ "group": "edges", "data": { "id": "167_125", "source": "167", "target": "125" } },{ "group": "edges", "data": { "id": "167_152", "source": "167", "target": "152" } },{ "group": "edges", "data": { "id": "167_71", "source": "167", "target": "71" } },{ "group": "edges", "data": { "id": "167_185", "source": "167", "target": "185" } },{ "group": "edges", "data": { "id": "167_68", "source": "167", "target": "68" } },{ "group": "edges", "data": { "id": "167_143", "source": "167", "target": "143" } },{ "group": "nodes", "data": { "id": "io.moquette.broker.subscriptions.SubscriptionIdentifier", "parent": "167" } },{ "group": "nodes", "data": { "id": "168" } },{ "group": "nodes", "data": { "id": "io.moquette.interception.messages.InterceptConnectionLostMessage", "parent": "168" } },{ "group": "edges", "data": { "id": "io.moquette.interception.messages.InterceptConnectionLostMessage_io.moquette.interception.messages.InterceptMessage", "source": "io.moquette.interception.messages.InterceptConnectionLostMessage", "target": "io.moquette.interception.messages.InterceptMessage" } },{ "group": "nodes", "data": { "id": "io.moquette.interception.messages.InterceptDisconnectMessage", "parent": "168" } },{ "group": "edges", "data": { "id": "io.moquette.interception.messages.InterceptDisconnectMessage_io.moquette.interception.messages.InterceptMessage", "source": "io.moquette.interception.messages.InterceptDisconnectMessage", "target": "io.moquette.interception.messages.InterceptMessage" } },{ "group": "nodes", "data": { "id": "io.moquette.interception.messages.InterceptMessage", "parent": "168" } },{ "group": "nodes", "data": { "id": "169" } },{ "group": "nodes", "data": { "id": "io.moquette.interception.AbstractInterceptHandler", "parent": "169" } },{ "group": "edges", "data": { "id": "169_168", "source": "169", "target": "168" } },{ "group": "edges", "data": { "id": "io.moquette.interception.AbstractInterceptHandler_io.moquette.interception.messages.InterceptPublishMessage", "source": "io.moquette.interception.AbstractInterceptHandler", "target": "io.moquette.interception.messages.InterceptPublishMessage" } },{ "group": "edges", "data": { "id": "169_173", "source": "169", "target": "173" } },{ "group": "edges", "data": { "id": "io.moquette.interception.AbstractInterceptHandler_io.moquette.interception.messages.InterceptUnsubscribeMessage", "source": "io.moquette.interception.AbstractInterceptHandler", "target": "io.moquette.interception.messages.InterceptUnsubscribeMessage" } },{ "group": "edges", "data": { "id": "169_68", "source": "169", "target": "68" } },{ "group": "nodes", "data": { "id": "io.moquette.interception.messages.InterceptAbstractMessage", "parent": "169" } },{ "group": "nodes", "data": { "id": "io.moquette.interception.messages.InterceptPublishMessage", "parent": "169" } },{ "group": "edges", "data": { "id": "io.moquette.interception.messages.InterceptPublishMessage_io.moquette.interception.messages.InterceptAbstractMessage", "source": "io.moquette.interception.messages.InterceptPublishMessage", "target": "io.moquette.interception.messages.InterceptAbstractMessage" } },{ "group": "nodes", "data": { "id": "io.moquette.interception.messages.InterceptUnsubscribeMessage", "parent": "169" } },{ "group": "nodes", "data": { "id": "171" } },{ "group": "nodes", "data": { "id": "io.moquette.broker.SessionEventLoopGroup", "parent": "171" } },{ "group": "edges", "data": { "id": "171_55", "source": "171", "target": "55" } },{ "group": "edges", "data": { "id": "171_124", "source": "171", "target": "124" } },{ "group": "edges", "data": { "id": "171_182", "source": "171", "target": "182" } },{ "group": "edges", "data": { "id": "171_51", "source": "171", "target": "51" } },{ "group": "nodes", "data": { "id": "173" } },{ "group": "nodes", "data": { "id": "io.moquette.broker.subscriptions.Subscription", "parent": "173" } },{ "group": "edges", "data": { "id": "173_125", "source": "173", "target": "125" } },{ "group": "nodes", "data": { "id": "io.moquette.interception.messages.InterceptSubscribeMessage", "parent": "173" } },{ "group": "edges", "data": { "id": "173_168", "source": "173", "target": "168" } },{ "group": "edges", "data": { "id": "io.moquette.interception.messages.InterceptSubscribeMessage_io.moquette.broker.subscriptions.Subscription", "source": "io.moquette.interception.messages.InterceptSubscribeMessage", "target": "io.moquette.broker.subscriptions.Subscription" } },{ "group": "nodes", "data": { "id": "174" } },{ "group": "nodes", "data": { "id": "io.moquette.broker.subscriptions.CTrie$NavigationAction", "parent": "174" } },{ "group": "nodes", "data": { "id": "175" } },{ "group": "nodes", "data": { "id": "io.moquette.broker.SessionMessageQueue", "parent": "175" } },{ "group": "nodes", "data": { "id": "io.moquette.persistence.H2QueueRepository", "parent": "175" } },{ "group": "edges", "data": { "id": "175_200", "source": "175", "target": "200" } },{ "group": "edges", "data": { "id": "io.moquette.persistence.H2QueueRepository_io.moquette.broker.SessionMessageQueue", "source": "io.moquette.persistence.H2QueueRepository", "target": "io.moquette.broker.SessionMessageQueue" } },{ "group": "edges", "data": { "id": "175_112", "source": "175", "target": "112" } },{ "group": "nodes", "data": { "id": "176" } },{ "group": "nodes", "data": { "id": "io.moquette.broker.security.AuthorizationsCollector", "parent": "176" } },{ "group": "edges", "data": { "id": "176_187", "source": "176", "target": "187" } },{ "group": "edges", "data": { "id": "176_165", "source": "176", "target": "165" } },{ "group": "edges", "data": { "id": "176_125", "source": "176", "target": "125" } },{ "group": "nodes", "data": { "id": "180" } },{ "group": "nodes", "data": { "id": "io.moquette.broker.InflightResender$ResendNotAckedPublishes", "parent": "180" } },{ "group": "nodes", "data": { "id": "181" } },{ "group": "nodes", "data": { "id": "io.moquette.broker.NewNettyMQTTHandler$1", "parent": "181" } },{ "group": "edges", "data": { "id": "io.moquette.broker.NewNettyMQTTHandler$1_io.moquette.broker.NewNettyMQTTHandler", "source": "io.moquette.broker.NewNettyMQTTHandler$1", "target": "io.moquette.broker.NewNettyMQTTHandler" } },{ "group": "nodes", "data": { "id": "io.moquette.broker.NewNettyMQTTHandler", "parent": "181" } },{ "group": "edges", "data": { "id": "181_73", "source": "181", "target": "73" } },{ "group": "edges", "data": { "id": "181_143", "source": "181", "target": "143" } },{ "group": "edges", "data": { "id": "181_68", "source": "181", "target": "68" } },{ "group": "edges", "data": { "id": "181_180", "source": "181", "target": "180" } },{ "group": "edges", "data": { "id": "181_21", "source": "181", "target": "21" } },{ "group": "nodes", "data": { "id": "182" } },{ "group": "nodes", "data": { "id": "io.moquette.broker.SessionCommand", "parent": "182" } },{ "group": "nodes", "data": { "id": "185" } },{ "group": "nodes", "data": { "id": "io.moquette.broker.ISessionsRepository$WillOptions", "parent": "185" } },{ "group": "nodes", "data": { "id": "io.moquette.persistence.H2SessionsRepository$1", "parent": "185" } },{ "group": "nodes", "data": { "id": "io.moquette.persistence.H2SessionsRepository$WillDataValueType", "parent": "185" } },{ "group": "edges", "data": { "id": "io.moquette.persistence.H2SessionsRepository$WillDataValueType_io.moquette.persistence.H2SessionsRepository$WillOptionsDataValueType", "source": "io.moquette.persistence.H2SessionsRepository$WillDataValueType", "target": "io.moquette.persistence.H2SessionsRepository$WillOptionsDataValueType" } },{ "group": "edges", "data": { "id": "io.moquette.persistence.H2SessionsRepository$WillDataValueType_io.moquette.broker.ISessionsRepository$WillOptions", "source": "io.moquette.persistence.H2SessionsRepository$WillDataValueType", "target": "io.moquette.broker.ISessionsRepository$WillOptions" } },{ "group": "edges", "data": { "id": "io.moquette.persistence.H2SessionsRepository$WillDataValueType_io.moquette.persistence.H2SessionsRepository$1", "source": "io.moquette.persistence.H2SessionsRepository$WillDataValueType", "target": "io.moquette.persistence.H2SessionsRepository$1" } },{ "group": "nodes", "data": { "id": "io.moquette.persistence.H2SessionsRepository$WillOptionsDataValueType", "parent": "185" } },{ "group": "edges", "data": { "id": "io.moquette.persistence.H2SessionsRepository$WillOptionsDataValueType_io.moquette.broker.ISessionsRepository$WillOptions", "source": "io.moquette.persistence.H2SessionsRepository$WillOptionsDataValueType", "target": "io.moquette.broker.ISessionsRepository$WillOptions" } },{ "group": "edges", "data": { "id": "io.moquette.persistence.H2SessionsRepository$WillOptionsDataValueType_io.moquette.persistence.H2SessionsRepository$1", "source": "io.moquette.persistence.H2SessionsRepository$WillOptionsDataValueType", "target": "io.moquette.persistence.H2SessionsRepository$1" } },{ "group": "nodes", "data": { "id": "187" } },{ "group": "nodes", "data": { "id": "io.moquette.broker.security.IAuthorizatorPolicy", "parent": "187" } },{ "group": "nodes", "data": { "id": "io.moquette.broker.security.PermitAllAuthorizatorPolicy", "parent": "187" } },{ "group": "edges", "data": { "id": "io.moquette.broker.security.PermitAllAuthorizatorPolicy_io.moquette.broker.security.IAuthorizatorPolicy", "source": "io.moquette.broker.security.PermitAllAuthorizatorPolicy", "target": "io.moquette.broker.security.IAuthorizatorPolicy" } },{ "group": "nodes", "data": { "id": "189" } },{ "group": "nodes", "data": { "id": "io.moquette.persistence.H2SubscriptionsRepository$SubscriptionOptionAndId", "parent": "189" } },{ "group": "edges", "data": { "id": "189_192", "source": "189", "target": "192" } },{ "group": "nodes", "data": { "id": "io.moquette.persistence.H2SubscriptionsRepository$SubscriptionOptionAndIdValueType", "parent": "189" } },{ "group": "edges", "data": { "id": "io.moquette.persistence.H2SubscriptionsRepository$SubscriptionOptionAndIdValueType_io.moquette.persistence.H2SubscriptionsRepository$SubscriptionOptionAndId", "source": "io.moquette.persistence.H2SubscriptionsRepository$SubscriptionOptionAndIdValueType", "target": "io.moquette.persistence.H2SubscriptionsRepository$SubscriptionOptionAndId" } },{ "group": "nodes", "data": { "id": "190" } },{ "group": "nodes", "data": { "id": "io.moquette.broker.subscriptions.CNode", "parent": "190" } },{ "group": "edges", "data": { "id": "190_173", "source": "190", "target": "173" } },{ "group": "edges", "data": { "id": "190_157", "source": "190", "target": "157" } },{ "group": "edges", "data": { "id": "190_146", "source": "190", "target": "146" } },{ "group": "edges", "data": { "id": "190_100", "source": "190", "target": "100" } },{ "group": "edges", "data": { "id": "190_167", "source": "190", "target": "167" } },{ "group": "edges", "data": { "id": "190_125", "source": "190", "target": "125" } },{ "group": "nodes", "data": { "id": "192" } },{ "group": "nodes", "data": { "id": "io.moquette.persistence.H2SubscriptionsRepository$1", "parent": "192" } },{ "group": "edges", "data": { "id": "io.moquette.persistence.H2SubscriptionsRepository$1_io.moquette.persistence.H2SubscriptionsRepository", "source": "io.moquette.persistence.H2SubscriptionsRepository$1", "target": "io.moquette.persistence.H2SubscriptionsRepository" } },{ "group": "nodes", "data": { "id": "io.moquette.persistence.H2SubscriptionsRepository$SubscriptionOptionValueType", "parent": "192" } },{ "group": "edges", "data": { "id": "io.moquette.persistence.H2SubscriptionsRepository$SubscriptionOptionValueType_io.moquette.persistence.H2SubscriptionsRepository", "source": "io.moquette.persistence.H2SubscriptionsRepository$SubscriptionOptionValueType", "target": "io.moquette.persistence.H2SubscriptionsRepository" } },{ "group": "nodes", "data": { "id": "io.moquette.persistence.H2SubscriptionsRepository$SubscriptionValueType", "parent": "192" } },{ "group": "edges", "data": { "id": "192_173", "source": "192", "target": "173" } },{ "group": "edges", "data": { "id": "192_167", "source": "192", "target": "167" } },{ "group": "edges", "data": { "id": "io.moquette.persistence.H2SubscriptionsRepository$SubscriptionValueType_io.moquette.persistence.H2SubscriptionsRepository$1", "source": "io.moquette.persistence.H2SubscriptionsRepository$SubscriptionValueType", "target": "io.moquette.persistence.H2SubscriptionsRepository$1" } },{ "group": "edges", "data": { "id": "192_125", "source": "192", "target": "125" } },{ "group": "edges", "data": { "id": "io.moquette.persistence.H2SubscriptionsRepository$SubscriptionValueType_io.moquette.persistence.H2SubscriptionsRepository$SubscriptionOptionValueType", "source": "io.moquette.persistence.H2SubscriptionsRepository$SubscriptionValueType", "target": "io.moquette.persistence.H2SubscriptionsRepository$SubscriptionOptionValueType" } },{ "group": "edges", "data": { "id": "io.moquette.persistence.H2SubscriptionsRepository$SubscriptionValueType_io.moquette.persistence.H2SubscriptionsRepository", "source": "io.moquette.persistence.H2SubscriptionsRepository$SubscriptionValueType", "target": "io.moquette.persistence.H2SubscriptionsRepository" } },{ "group": "nodes", "data": { "id": "io.moquette.persistence.H2SubscriptionsRepository", "parent": "192" } },{ "group": "edges", "data": { "id": "192_194", "source": "192", "target": "194" } },{ "group": "edges", "data": { "id": "192_30", "source": "192", "target": "30" } },{ "group": "edges", "data": { "id": "192_157", "source": "192", "target": "157" } },{ "group": "edges", "data": { "id": "192_146", "source": "192", "target": "146" } },{ "group": "nodes", "data": { "id": "193" } },{ "group": "nodes", "data": { "id": "io.moquette.broker.InflightResender$WriterIdleTimeoutTask", "parent": "193" } },{ "group": "nodes", "data": { "id": "194" } },{ "group": "nodes", "data": { "id": "io.moquette.broker.ISubscriptionsRepository", "parent": "194" } },{ "group": "edges", "data": { "id": "194_173", "source": "194", "target": "173" } },{ "group": "edges", "data": { "id": "194_157", "source": "194", "target": "157" } },{ "group": "edges", "data": { "id": "194_125", "source": "194", "target": "125" } },{ "group": "edges", "data": { "id": "194_167", "source": "194", "target": "167" } },{ "group": "edges", "data": { "id": "194_146", "source": "194", "target": "146" } },{ "group": "nodes", "data": { "id": "io.moquette.broker.subscriptions.CTrieSubscriptionDirectory", "parent": "194" } },{ "group": "edges", "data": { "id": "194_98", "source": "194", "target": "98" } },{ "group": "edges", "data": { "id": "io.moquette.broker.subscriptions.CTrieSubscriptionDirectory_io.moquette.broker.ISubscriptionsRepository", "source": "io.moquette.broker.subscriptions.CTrieSubscriptionDirectory", "target": "io.moquette.broker.ISubscriptionsRepository" } },{ "group": "edges", "data": { "id": "194_100", "source": "194", "target": "100" } },{ "group": "nodes", "data": { "id": "195" } },{ "group": "nodes", "data": { "id": "io.moquette.persistence.EnqueuedMessageValueType$MessageType", "parent": "195" } },{ "group": "edges", "data": { "id": "io.moquette.persistence.EnqueuedMessageValueType$MessageType_io.moquette.persistence.EnqueuedMessageValueType", "source": "io.moquette.persistence.EnqueuedMessageValueType$MessageType", "target": "io.moquette.persistence.EnqueuedMessageValueType" } },{ "group": "nodes", "data": { "id": "io.moquette.persistence.EnqueuedMessageValueType", "parent": "195" } },{ "group": "edges", "data": { "id": "195_24", "source": "195", "target": "24" } },{ "group": "edges", "data": { "id": "195_132", "source": "195", "target": "132" } },{ "group": "edges", "data": { "id": "195_112", "source": "195", "target": "112" } },{ "group": "edges", "data": { "id": "195_152", "source": "195", "target": "152" } },{ "group": "edges", "data": { "id": "195_9", "source": "195", "target": "9" } },{ "group": "edges", "data": { "id": "195_125", "source": "195", "target": "125" } },{ "group": "edges", "data": { "id": "195_14", "source": "195", "target": "14" } },{ "group": "nodes", "data": { "id": "198" } },{ "group": "nodes", "data": { "id": "io.moquette.broker.ISslContextCreator", "parent": "198" } },{ "group": "nodes", "data": { "id": "io.moquette.broker.security.FileAuthenticator", "parent": "198" } },{ "group": "edges", "data": { "id": "198_119", "source": "198", "target": "119" } },{ "group": "edges", "data": { "id": "198_109", "source": "198", "target": "109" } },{ "group": "nodes", "data": { "id": "200" } },{ "group": "nodes", "data": { "id": "io.moquette.broker.IQueueRepository", "parent": "200" } },{ "group": "edges", "data": { "id": "200_112", "source": "200", "target": "112" } },{ "group": "nodes", "data": { "id": "io.moquette.persistence.H2Builder", "parent": "200" } },{ "group": "edges", "data": { "id": "200_194", "source": "200", "target": "194" } },{ "group": "edges", "data": { "id": "io.moquette.persistence.H2Builder_io.moquette.broker.IQueueRepository", "source": "io.moquette.persistence.H2Builder", "target": "io.moquette.broker.IQueueRepository" } },{ "group": "edges", "data": { "id": "200_87", "source": "200", "target": "87" } },{ "group": "edges", "data": { "id": "200_139", "source": "200", "target": "139" } },{ "group": "edges", "data": { "id": "200_192", "source": "200", "target": "192" } },{ "group": "edges", "data": { "id": "200_132", "source": "200", "target": "132" } },{ "group": "edges", "data": { "id": "200_10", "source": "200", "target": "10" } },{ "group": "nodes", "data": { "id": "203" } },{ "group": "nodes", "data": { "id": "io.moquette.persistence.H2RetainedRepository$1", "parent": "203" } }]
