[{ "group": "nodes", "data": { "id": "1" } },{ "group": "nodes", "data": { "id": "org.joda.money.format.LiteralPrinterParser", "parent": "1" } },{ "group": "edges", "data": { "id": "1_26", "source": "1", "target": "26" } },{ "group": "edges", "data": { "id": "org.joda.money.format.LiteralPrinterParser_org.joda.money.format.MoneyParser", "source": "org.joda.money.format.LiteralPrinterParser", "target": "org.joda.money.format.MoneyParser" } },{ "group": "edges", "data": { "id": "1_24", "source": "1", "target": "24" } },{ "group": "edges", "data": { "id": "1_2", "source": "1", "target": "2" } },{ "group": "edges", "data": { "id": "1_23", "source": "1", "target": "23" } },{ "group": "nodes", "data": { "id": "org.joda.money.format.MoneyParser", "parent": "1" } },{ "group": "nodes", "data": { "id": "2" } },{ "group": "nodes", "data": { "id": "org.joda.money.CurrencyMismatchException", "parent": "2" } },{ "group": "edges", "data": { "id": "2_15", "source": "2", "target": "15" } },{ "group": "nodes", "data": { "id": "org.joda.money.BigMoney", "parent": "2" } },{ "group": "edges", "data": { "id": "2_19", "source": "2", "target": "19" } },{ "group": "edges", "data": { "id": "2_6", "source": "2", "target": "6" } },{ "group": "edges", "data": { "id": "org.joda.money.BigMoney_org.joda.money.CurrencyMismatchException", "source": "org.joda.money.BigMoney", "target": "org.joda.money.CurrencyMismatchException" } },{ "group": "nodes", "data": { "id": "4" } },{ "group": "nodes", "data": { "id": "org.joda.money.format.MoneyFormatterBuilder$Singletons", "parent": "4" } },{ "group": "edges", "data": { "id": "4_26", "source": "4", "target": "26" } },{ "group": "edges", "data": { "id": "4_1", "source": "4", "target": "1" } },{ "group": "edges", "data": { "id": "4_8", "source": "4", "target": "8" } },{ "group": "edges", "data": { "id": "org.joda.money.format.MoneyFormatterBuilder$Singletons_org.joda.money.format.MoneyFormatterBuilder$Singletons$2", "source": "org.joda.money.format.MoneyFormatterBuilder$Singletons", "target": "org.joda.money.format.MoneyFormatterBuilder$Singletons$2" } },{ "group": "edges", "data": { "id": "4_9", "source": "4", "target": "9" } },{ "group": "edges", "data": { "id": "4_25", "source": "4", "target": "25" } },{ "group": "nodes", "data": { "id": "org.joda.money.format.MoneyFormatterBuilder$Singletons$2", "parent": "4" } },{ "group": "edges", "data": { "id": "4_24", "source": "4", "target": "24" } },{ "group": "edges", "data": { "id": "4_2", "source": "4", "target": "2" } },{ "group": "edges", "data": { "id": "4_23", "source": "4", "target": "23" } },{ "group": "edges", "data": { "id": "4_15", "source": "4", "target": "15" } },{ "group": "nodes", "data": { "id": "6" } },{ "group": "nodes", "data": { "id": "org.joda.money.MoneyUtils", "parent": "6" } },{ "group": "edges", "data": { "id": "6_19", "source": "6", "target": "19" } },{ "group": "edges", "data": { "id": "org.joda.money.MoneyUtils_org.joda.money.Money", "source": "org.joda.money.MoneyUtils", "target": "org.joda.money.Money" } },{ "group": "nodes", "data": { "id": "org.joda.money.Money", "parent": "6" } },{ "group": "edges", "data": { "id": "6_15", "source": "6", "target": "15" } },{ "group": "nodes", "data": { "id": "8" } },{ "group": "nodes", "data": { "id": "org.joda.money.format.MoneyFormatterBuilder$Singletons$1", "parent": "8" } },{ "group": "edges", "data": { "id": "8_24", "source": "8", "target": "24" } },{ "group": "edges", "data": { "id": "8_2", "source": "8", "target": "2" } },{ "group": "edges", "data": { "id": "8_23", "source": "8", "target": "23" } },{ "group": "edges", "data": { "id": "org.joda.money.format.MoneyFormatterBuilder$Singletons$1_org.joda.money.IllegalCurrencyException", "source": "org.joda.money.format.MoneyFormatterBuilder$Singletons$1", "target": "org.joda.money.IllegalCurrencyException" } },{ "group": "edges", "data": { "id": "8_15", "source": "8", "target": "15" } },{ "group": "edges", "data": { "id": "8_25", "source": "8", "target": "25" } },{ "group": "nodes", "data": { "id": "org.joda.money.IllegalCurrencyException", "parent": "8" } },{ "group": "nodes", "data": { "id": "9" } },{ "group": "nodes", "data": { "id": "org.joda.money.format.MoneyFormatterBuilder$Singletons$3", "parent": "9" } },{ "group": "edges", "data": { "id": "9_24", "source": "9", "target": "24" } },{ "group": "edges", "data": { "id": "9_2", "source": "9", "target": "2" } },{ "group": "edges", "data": { "id": "9_23", "source": "9", "target": "23" } },{ "group": "edges", "data": { "id": "9_8", "source": "9", "target": "8" } },{ "group": "edges", "data": { "id": "9_15", "source": "9", "target": "15" } },{ "group": "edges", "data": { "id": "9_25", "source": "9", "target": "25" } },{ "group": "nodes", "data": { "id": "org.joda.money.format.MoneyFormatException", "parent": "9" } },{ "group": "nodes", "data": { "id": "15" } },{ "group": "nodes", "data": { "id": "org.joda.money.Ser", "parent": "15" } },{ "group": "edges", "data": { "id": "org.joda.money.Ser_org.joda.money.CurrencyUnit", "source": "org.joda.money.Ser", "target": "org.joda.money.CurrencyUnit" } },{ "group": "nodes", "data": { "id": "org.joda.money.CurrencyUnit", "parent": "15" } },{ "group": "edges", "data": { "id": "15_22", "source": "15", "target": "22" } },{ "group": "edges", "data": { "id": "15_17", "source": "15", "target": "17" } },{ "group": "nodes", "data": { "id": "17" } },{ "group": "nodes", "data": { "id": "org.joda.money.DefaultCurrencyUnitDataProvider", "parent": "17" } },{ "group": "edges", "data": { "id": "17_22", "source": "17", "target": "22" } },{ "group": "nodes", "data": { "id": "19" } },{ "group": "nodes", "data": { "id": "org.joda.money.BigMoneyProvider", "parent": "19" } },{ "group": "nodes", "data": { "id": "22" } },{ "group": "nodes", "data": { "id": "org.joda.money.CurrencyUnitDataProvider", "parent": "22" } },{ "group": "nodes", "data": { "id": "23" } },{ "group": "nodes", "data": { "id": "org.joda.money.format.MoneyFormatter", "parent": "23" } },{ "group": "edges", "data": { "id": "org.joda.money.format.MoneyFormatter_org.joda.money.format.MultiPrinterParser", "source": "org.joda.money.format.MoneyFormatter", "target": "org.joda.money.format.MultiPrinterParser" } },{ "group": "edges", "data": { "id": "23_26", "source": "23", "target": "26" } },{ "group": "edges", "data": { "id": "23_19", "source": "23", "target": "19" } },{ "group": "edges", "data": { "id": "23_2", "source": "23", "target": "2" } },{ "group": "edges", "data": { "id": "23_24", "source": "23", "target": "24" } },{ "group": "edges", "data": { "id": "org.joda.money.format.MoneyFormatter_org.joda.money.format.MoneyParseContext", "source": "org.joda.money.format.MoneyFormatter", "target": "org.joda.money.format.MoneyParseContext" } },{ "group": "edges", "data": { "id": "23_6", "source": "23", "target": "6" } },{ "group": "nodes", "data": { "id": "org.joda.money.format.MoneyParseContext", "parent": "23" } },{ "group": "edges", "data": { "id": "23_15", "source": "23", "target": "15" } },{ "group": "nodes", "data": { "id": "org.joda.money.format.MultiPrinterParser", "parent": "23" } },{ "group": "edges", "data": { "id": "23_25", "source": "23", "target": "25" } },{ "group": "edges", "data": { "id": "org.joda.money.format.MultiPrinterParser_org.joda.money.format.MoneyParseContext", "source": "org.joda.money.format.MultiPrinterParser", "target": "org.joda.money.format.MoneyParseContext" } },{ "group": "nodes", "data": { "id": "24" } },{ "group": "nodes", "data": { "id": "org.joda.money.format.MoneyPrintContext", "parent": "24" } },{ "group": "nodes", "data": { "id": "org.joda.money.format.SignedPrinterParser", "parent": "24" } },{ "group": "edges", "data": { "id": "24_26", "source": "24", "target": "26" } },{ "group": "edges", "data": { "id": "org.joda.money.format.SignedPrinterParser_org.joda.money.format.MoneyPrintContext", "source": "org.joda.money.format.SignedPrinterParser", "target": "org.joda.money.format.MoneyPrintContext" } },{ "group": "edges", "data": { "id": "24_2", "source": "24", "target": "2" } },{ "group": "nodes", "data": { "id": "org.joda.money.format.AmountPrinterParser", "parent": "24" } },{ "group": "edges", "data": { "id": "24_27", "source": "24", "target": "27" } },{ "group": "edges", "data": { "id": "org.joda.money.format.AmountPrinterParser_org.joda.money.format.MoneyPrintContext", "source": "org.joda.money.format.AmountPrinterParser", "target": "org.joda.money.format.MoneyPrintContext" } },{ "group": "nodes", "data": { "id": "25" } },{ "group": "nodes", "data": { "id": "org.joda.money.format.MoneyFormatterBuilder", "parent": "25" } },{ "group": "edges", "data": { "id": "25_26", "source": "25", "target": "26" } },{ "group": "edges", "data": { "id": "25_1", "source": "25", "target": "1" } },{ "group": "edges", "data": { "id": "25_24", "source": "25", "target": "24" } },{ "group": "edges", "data": { "id": "25_27", "source": "25", "target": "27" } },{ "group": "nodes", "data": { "id": "26" } },{ "group": "nodes", "data": { "id": "org.joda.money.format.MoneyPrinter", "parent": "26" } },{ "group": "edges", "data": { "id": "26_2", "source": "26", "target": "2" } },{ "group": "nodes", "data": { "id": "org.joda.money.format.MoneyFormatterBuilder$SingletonPrinters", "parent": "26" } },{ "group": "edges", "data": { "id": "org.joda.money.format.MoneyFormatterBuilder$SingletonPrinters_org.joda.money.format.MoneyPrinter", "source": "org.joda.money.format.MoneyFormatterBuilder$SingletonPrinters", "target": "org.joda.money.format.MoneyPrinter" } },{ "group": "edges", "data": { "id": "26_15", "source": "26", "target": "15" } },{ "group": "nodes", "data": { "id": "27" } },{ "group": "nodes", "data": { "id": "org.joda.money.format.MoneyAmountStyle", "parent": "27" } },{ "group": "edges", "data": { "id": "org.joda.money.format.MoneyAmountStyle_org.joda.money.format.GroupingStyle", "source": "org.joda.money.format.MoneyAmountStyle", "target": "org.joda.money.format.GroupingStyle" } },{ "group": "edges", "data": { "id": "27_23", "source": "27", "target": "23" } },{ "group": "nodes", "data": { "id": "org.joda.money.format.GroupingStyle", "parent": "27" } }]
